{
    "data": [
        {
            "building": "ARC",
            "term": 1159,
            "last_updated": "2015-08-19T22:04:07-04:00",
            "catalog_number": "110",
            "end_date": null,
            "title": "Visual Communication 1",
            "section": "STU 001",
            "instructors": [
                "Dowling,Paul"
            ],
            "weekdays": "F",
            "start_date": null,
            "room": "1101",
            "end_time": "09:50",
            "enrollment_total": 77,
            "class_number": 4970,
            "start_time": "09:00",
            "subject": "ARCH"
        },
        {
            "building": "ARC",
            "term": 1159,
            "last_updated": "2015-08-19T22:04:07-04:00",
            "catalog_number": "125",
            "end_date": null,
            "title": "Principles of Environmental Design",
            "section": "LEC 001",
            "instructors": [
                "Boake,Terri"
            ],
            "weekdays": "W",
            "start_date": null,
            "room": "1101",
            "end_time": "16:50",
            "enrollment_total": 77,
            "class_number": 8548,
            "start_time": "14:00",
            "subject": "ARCH"
        },
        {
            "building": "ARC",
            "term": 1159,
            "last_updated": "2015-08-19T22:04:07-04:00",
            "catalog_number": "212",
            "end_date": null,
            "title": "Digital Fabrication",
            "section": "LEC 001",
            "instructors": [],
            "weekdays": "W",
            "start_date": null,
            "room": "1101",
            "end_time": "12:50",
            "enrollment_total": 81,
            "class_number": 8549,
            "start_time": "10:00",
            "subject": "ARCH"
        },
        {
            "building": "ARC",
            "term": 1159,
            "last_updated": "2015-08-19T22:04:08-04:00",
            "catalog_number": "260",
            "end_date": null,
            "title": "Principles of Structures",
            "section": "LEC 001",
            "instructors": [
                "English,Elizabeth"
            ],
            "weekdays": "T",
            "start_date": null,
            "room": "1101",
            "end_time": "12:50",
            "enrollment_total": 79,
            "class_number": 4972,
            "start_time": "09:00",
            "subject": "ARCH"
        },
        {
            "building": "ARC",
            "term": 1159,
            "last_updated": "2015-08-19T22:04:08-04:00",
            "catalog_number": "260",
            "end_date": null,
            "title": "Principles of Structures",
            "section": "LEC 001",
            "instructors": [
                "English,Elizabeth"
            ],
            "weekdays": "F",
            "start_date": null,
            "room": "1101",
            "end_time": "15:50",
            "enrollment_total": 79,
            "class_number": 4972,
            "start_time": "14:00",
            "subject": "ARCH"
        },
        {
            "building": "ARC",
            "term": 1159,
            "last_updated": "2015-08-19T22:04:08-04:00",
            "catalog_number": "263",
            "end_date": null,
            "title": "Integrated Enviro Systems",
            "section": "LEC 001",
            "instructors": [
                "Lukachko,Christian Alexander",
                "Schumacher,Christopher James"
            ],
            "weekdays": "W",
            "start_date": null,
            "room": "1101",
            "end_time": "21:20",
            "enrollment_total": 81,
            "class_number": 8550,
            "start_time": "18:30",
            "subject": "ARCH"
        },
        {
            "building": "ARC",
            "term": 1159,
            "last_updated": "2015-08-19T22:04:08-04:00",
            "catalog_number": "342",
            "end_date": null,
            "title": "Modern Architecture",
            "section": "LEC 001",
            "instructors": [
                "Macdonald,Marie-Paule"
            ],
            "weekdays": "T",
            "start_date": null,
            "room": "1101",
            "end_time": "20:50",
            "enrollment_total": 60,
            "class_number": 4993,
            "start_time": "18:00",
            "subject": "ARCH"
        },
        {
            "building": "ARC",
            "term": 1159,
            "last_updated": "2015-08-19T22:04:09-04:00",
            "catalog_number": "465",
            "end_date": null,
            "title": "Advanced Structures",
            "section": "LEC 001",
            "instructors": [
                "English,Elizabeth"
            ],
            "weekdays": "F",
            "start_date": null,
            "room": "1101",
            "end_time": "12:50",
            "enrollment_total": 58,
            "class_number": 8565,
            "start_time": "10:00",
            "subject": "ARCH"
        },
        {
            "building": "ARC",
            "term": 1159,
            "last_updated": "2015-08-19T22:04:09-04:00",
            "catalog_number": "465",
            "end_date": null,
            "title": "Advanced Structures",
            "section": "TUT 101",
            "instructors": [
                "English,Elizabeth"
            ],
            "weekdays": "T",
            "start_date": null,
            "room": "1101",
            "end_time": "15:50",
            "enrollment_total": 58,
            "class_number": 8566,
            "start_time": "14:00",
            "subject": "ARCH"
        },
        {
            "building": "ARC",
            "term": 1159,
            "last_updated": "2015-08-19T22:06:22-04:00",
            "catalog_number": "155",
            "end_date": null,
            "title": "Intensive Introductory Italian Language",
            "section": "LEC 001",
            "instructors": [
                "Cauchi-Santoro,Roberta"
            ],
            "weekdays": "M",
            "start_date": null,
            "room": "1101",
            "end_time": "19:50",
            "enrollment_total": 13,
            "class_number": 7555,
            "start_time": "18:30",
            "subject": "ITAL"
        },
        {
            "building": "ARC",
            "term": 1159,
            "last_updated": "2015-08-19T22:09:50-04:00",
            "catalog_number": "610",
            "end_date": null,
            "title": "Arch Research and Analysis",
            "section": "LEC 001",
            "instructors": [
                "El Khafif,Mona"
            ],
            "weekdays": "M",
            "start_date": null,
            "room": "1101",
            "end_time": "16:50",
            "enrollment_total": 25,
            "class_number": 5524,
            "start_time": "14:00",
            "subject": "ARCH"
        },
        {
            "building": "ARC",
            "term": 1159,
            "last_updated": "2015-08-19T22:09:51-04:00",
            "catalog_number": "642",
            "end_date": null,
            "title": "The Practice of Criticism in Creative Design",
            "section": "LEC 001",
            "instructors": [
                "Macdonald,Marie-Paule"
            ],
            "weekdays": "T",
            "start_date": null,
            "room": "1101",
            "end_time": "21:50",
            "enrollment_total": 7,
            "class_number": 8576,
            "start_time": "19:00",
            "subject": "ARCH"
        }
    ]
}