{
    "data": [
        {
            "building": "DWE",
            "term": 1159,
            "last_updated": "2015-08-19T22:04:32-04:00",
            "catalog_number": "102",
            "end_date": null,
            "title": "Chemistry for Engineers",
            "section": "LEC 003",
            "instructors": [
                "Legge,Raymond L"
            ],
            "weekdays": "Th",
            "start_date": null,
            "room": "1501",
            "end_time": "09:20",
            "enrollment_total": 118,
            "class_number": 4770,
            "start_time": "08:30",
            "subject": "CHE"
        },
        {
            "building": "DWE",
            "term": 1159,
            "last_updated": "2015-08-19T22:04:32-04:00",
            "catalog_number": "102",
            "end_date": null,
            "title": "Chemistry for Engineers",
            "section": "LEC 007",
            "instructors": [
                "Chen,Pu"
            ],
            "weekdays": "MTTh",
            "start_date": null,
            "room": "1501",
            "end_time": "15:20",
            "enrollment_total": 117,
            "class_number": 4789,
            "start_time": "14:30",
            "subject": "CHE"
        },
        {
            "building": "DWE",
            "term": 1159,
            "last_updated": "2015-08-19T22:04:32-04:00",
            "catalog_number": "102",
            "end_date": "10/01",
            "title": "Chemistry for Engineers",
            "section": "LEC 007",
            "instructors": [
                "Chen,Pu"
            ],
            "weekdays": "Th",
            "start_date": "10/01",
            "room": "1501",
            "end_time": "16:20",
            "enrollment_total": 117,
            "class_number": 4789,
            "start_time": "15:30",
            "subject": "CHE"
        },
        {
            "building": "DWE",
            "term": 1159,
            "last_updated": "2015-08-19T22:04:32-04:00",
            "catalog_number": "102",
            "end_date": "10/15",
            "title": "Chemistry for Engineers",
            "section": "LEC 007",
            "instructors": [
                "Chen,Pu"
            ],
            "weekdays": "Th",
            "start_date": "10/15",
            "room": "1501",
            "end_time": "16:20",
            "enrollment_total": 117,
            "class_number": 4789,
            "start_time": "15:30",
            "subject": "CHE"
        },
        {
            "building": "DWE",
            "term": 1159,
            "last_updated": "2015-08-19T22:04:32-04:00",
            "catalog_number": "102",
            "end_date": "10/29",
            "title": "Chemistry for Engineers",
            "section": "LEC 007",
            "instructors": [
                "Chen,Pu"
            ],
            "weekdays": "Th",
            "start_date": "10/29",
            "room": "1501",
            "end_time": "16:20",
            "enrollment_total": 117,
            "class_number": 4789,
            "start_time": "15:30",
            "subject": "CHE"
        },
        {
            "building": "DWE",
            "term": 1159,
            "last_updated": "2015-08-19T22:04:32-04:00",
            "catalog_number": "102",
            "end_date": "11/12",
            "title": "Chemistry for Engineers",
            "section": "LEC 007",
            "instructors": [
                "Chen,Pu"
            ],
            "weekdays": "Th",
            "start_date": "11/12",
            "room": "1501",
            "end_time": "16:20",
            "enrollment_total": 117,
            "class_number": 4789,
            "start_time": "15:30",
            "subject": "CHE"
        },
        {
            "building": "DWE",
            "term": 1159,
            "last_updated": "2015-08-19T22:04:32-04:00",
            "catalog_number": "102",
            "end_date": "11/26",
            "title": "Chemistry for Engineers",
            "section": "LEC 007",
            "instructors": [
                "Chen,Pu"
            ],
            "weekdays": "Th",
            "start_date": "11/26",
            "room": "1501",
            "end_time": "16:20",
            "enrollment_total": 117,
            "class_number": 4789,
            "start_time": "15:30",
            "subject": "CHE"
        },
        {
            "building": "DWE",
            "term": 1159,
            "last_updated": "2015-08-19T22:04:32-04:00",
            "catalog_number": "102",
            "end_date": null,
            "title": "Chemistry for Engineers",
            "section": "LEC 008",
            "instructors": [
                "Chen,Pu"
            ],
            "weekdays": "M",
            "start_date": null,
            "room": "1501",
            "end_time": "10:20",
            "enrollment_total": 117,
            "class_number": 4834,
            "start_time": "09:30",
            "subject": "CHE"
        },
        {
            "building": "DWE",
            "term": 1159,
            "last_updated": "2015-08-19T22:04:32-04:00",
            "catalog_number": "102",
            "end_date": null,
            "title": "Chemistry for Engineers",
            "section": "LEC 008",
            "instructors": [
                "Chen,Pu"
            ],
            "weekdays": "T",
            "start_date": null,
            "room": "1501",
            "end_time": "10:20",
            "enrollment_total": 117,
            "class_number": 4834,
            "start_time": "09:30",
            "subject": "CHE"
        },
        {
            "building": "DWE",
            "term": 1159,
            "last_updated": "2015-08-19T22:04:32-04:00",
            "catalog_number": "102",
            "end_date": "09/29",
            "title": "Chemistry for Engineers",
            "section": "LEC 008",
            "instructors": [
                "Chen,Pu"
            ],
            "weekdays": "T",
            "start_date": "09/29",
            "room": "1501",
            "end_time": "12:20",
            "enrollment_total": 117,
            "class_number": 4834,
            "start_time": "11:30",
            "subject": "CHE"
        },
        {
            "building": "DWE",
            "term": 1159,
            "last_updated": "2015-08-19T22:04:32-04:00",
            "catalog_number": "102",
            "end_date": "10/13",
            "title": "Chemistry for Engineers",
            "section": "LEC 008",
            "instructors": [
                "Chen,Pu"
            ],
            "weekdays": "T",
            "start_date": "10/13",
            "room": "1501",
            "end_time": "12:20",
            "enrollment_total": 117,
            "class_number": 4834,
            "start_time": "11:30",
            "subject": "CHE"
        },
        {
            "building": "DWE",
            "term": 1159,
            "last_updated": "2015-08-19T22:04:32-04:00",
            "catalog_number": "102",
            "end_date": "10/27",
            "title": "Chemistry for Engineers",
            "section": "LEC 008",
            "instructors": [
                "Chen,Pu"
            ],
            "weekdays": "T",
            "start_date": "10/27",
            "room": "1501",
            "end_time": "12:20",
            "enrollment_total": 117,
            "class_number": 4834,
            "start_time": "11:30",
            "subject": "CHE"
        },
        {
            "building": "DWE",
            "term": 1159,
            "last_updated": "2015-08-19T22:04:32-04:00",
            "catalog_number": "102",
            "end_date": "11/10",
            "title": "Chemistry for Engineers",
            "section": "LEC 008",
            "instructors": [
                "Chen,Pu"
            ],
            "weekdays": "T",
            "start_date": "11/10",
            "room": "1501",
            "end_time": "12:20",
            "enrollment_total": 117,
            "class_number": 4834,
            "start_time": "11:30",
            "subject": "CHE"
        },
        {
            "building": "DWE",
            "term": 1159,
            "last_updated": "2015-08-19T22:04:32-04:00",
            "catalog_number": "102",
            "end_date": "11/24",
            "title": "Chemistry for Engineers",
            "section": "LEC 008",
            "instructors": [
                "Chen,Pu"
            ],
            "weekdays": "T",
            "start_date": "11/24",
            "room": "1501",
            "end_time": "12:20",
            "enrollment_total": 117,
            "class_number": 4834,
            "start_time": "11:30",
            "subject": "CHE"
        },
        {
            "building": "DWE",
            "term": 1159,
            "last_updated": "2015-08-19T22:04:46-04:00",
            "catalog_number": "104",
            "end_date": null,
            "title": "Mechanics 1",
            "section": "LEC 002",
            "instructors": [
                "Brodland,G. Wayne"
            ],
            "weekdays": "Th",
            "start_date": null,
            "room": "1501",
            "end_time": "10:50",
            "enrollment_total": 122,
            "class_number": 8150,
            "start_time": "09:30",
            "subject": "CIVE"
        },
        {
            "building": "DWE",
            "term": 1159,
            "last_updated": "2015-08-19T22:04:47-04:00",
            "catalog_number": "313",
            "end_date": null,
            "title": "Structural Concrete Design 1",
            "section": "TUT 101",
            "instructors": [
                "West,Jeffrey S"
            ],
            "weekdays": "W",
            "start_date": null,
            "room": "1501",
            "end_time": "16:20",
            "enrollment_total": 108,
            "class_number": 4823,
            "start_time": "14:30",
            "subject": "CIVE"
        },
        {
            "building": "DWE",
            "term": 1159,
            "last_updated": "2015-08-19T22:05:37-04:00",
            "catalog_number": "310",
            "end_date": null,
            "title": "Environmental Analysis and Solutions V: Environmental Thought",
            "section": "LEC 001",
            "instructors": [
                "Gibson,Robert B"
            ],
            "weekdays": "T",
            "start_date": null,
            "room": "1501",
            "end_time": "14:20",
            "enrollment_total": 61,
            "class_number": 5604,
            "start_time": "12:30",
            "subject": "ERS"
        },
        {
            "building": "DWE",
            "term": 1159,
            "last_updated": "2015-08-19T22:05:50-04:00",
            "catalog_number": "119",
            "end_date": "09/21",
            "title": "Problems Seminar",
            "section": "SEM 007",
            "instructors": [],
            "weekdays": "M",
            "start_date": "09/21",
            "room": "1501",
            "end_time": "16:20",
            "enrollment_total": 0,
            "class_number": 5021,
            "start_time": "15:30",
            "subject": "GENE"
        },
        {
            "building": "DWE",
            "term": 1159,
            "last_updated": "2015-08-19T22:05:50-04:00",
            "catalog_number": "119",
            "end_date": "10/05",
            "title": "Problems Seminar",
            "section": "SEM 007",
            "instructors": [],
            "weekdays": "M",
            "start_date": "10/05",
            "room": "1501",
            "end_time": "16:20",
            "enrollment_total": 0,
            "class_number": 5021,
            "start_time": "15:30",
            "subject": "GENE"
        },
        {
            "building": "DWE",
            "term": 1159,
            "last_updated": "2015-08-19T22:05:50-04:00",
            "catalog_number": "119",
            "end_date": "11/02",
            "title": "Problems Seminar",
            "section": "SEM 007",
            "instructors": [],
            "weekdays": "M",
            "start_date": "11/02",
            "room": "1501",
            "end_time": "16:20",
            "enrollment_total": 0,
            "class_number": 5021,
            "start_time": "15:30",
            "subject": "GENE"
        },
        {
            "building": "DWE",
            "term": 1159,
            "last_updated": "2015-08-19T22:05:50-04:00",
            "catalog_number": "119",
            "end_date": "09/25",
            "title": "Problems Seminar",
            "section": "SEM 008",
            "instructors": [],
            "weekdays": "F",
            "start_date": "09/25",
            "room": "1501",
            "end_time": "10:20",
            "enrollment_total": 0,
            "class_number": 5022,
            "start_time": "09:30",
            "subject": "GENE"
        },
        {
            "building": "DWE",
            "term": 1159,
            "last_updated": "2015-08-19T22:05:50-04:00",
            "catalog_number": "119",
            "end_date": "10/09",
            "title": "Problems Seminar",
            "section": "SEM 008",
            "instructors": [],
            "weekdays": "F",
            "start_date": "10/09",
            "room": "1501",
            "end_time": "10:20",
            "enrollment_total": 0,
            "class_number": 5022,
            "start_time": "09:30",
            "subject": "GENE"
        },
        {
            "building": "DWE",
            "term": 1159,
            "last_updated": "2015-08-19T22:05:50-04:00",
            "catalog_number": "119",
            "end_date": "11/06",
            "title": "Problems Seminar",
            "section": "SEM 008",
            "instructors": [],
            "weekdays": "F",
            "start_date": "11/06",
            "room": "1501",
            "end_time": "10:20",
            "enrollment_total": 0,
            "class_number": 5022,
            "start_time": "09:30",
            "subject": "GENE"
        },
        {
            "building": "DWE",
            "term": 1159,
            "last_updated": "2015-08-19T22:06:41-04:00",
            "catalog_number": "115",
            "end_date": null,
            "title": "Linear Algebra for Engineering",
            "section": "LEC 002",
            "instructors": [],
            "weekdays": "T",
            "start_date": null,
            "room": "1501",
            "end_time": "16:20",
            "enrollment_total": 119,
            "class_number": 5987,
            "start_time": "15:30",
            "subject": "MATH"
        },
        {
            "building": "DWE",
            "term": 1159,
            "last_updated": "2015-08-19T22:06:41-04:00",
            "catalog_number": "115",
            "end_date": null,
            "title": "Linear Algebra for Engineering",
            "section": "LEC 002",
            "instructors": [],
            "weekdays": "Th",
            "start_date": null,
            "room": "1501",
            "end_time": "14:20",
            "enrollment_total": 119,
            "class_number": 5987,
            "start_time": "13:30",
            "subject": "MATH"
        },
        {
            "building": "DWE",
            "term": 1159,
            "last_updated": "2015-08-19T22:06:41-04:00",
            "catalog_number": "115",
            "end_date": null,
            "title": "Linear Algebra for Engineering",
            "section": "LEC 002",
            "instructors": [],
            "weekdays": "F",
            "start_date": null,
            "room": "1501",
            "end_time": "15:20",
            "enrollment_total": 119,
            "class_number": 5987,
            "start_time": "14:30",
            "subject": "MATH"
        },
        {
            "building": "DWE",
            "term": 1159,
            "last_updated": "2015-08-19T22:06:41-04:00",
            "catalog_number": "115",
            "end_date": "09/28",
            "title": "Linear Algebra for Engineering",
            "section": "LEC 002",
            "instructors": [],
            "weekdays": "M",
            "start_date": "09/28",
            "room": "1501",
            "end_time": "16:20",
            "enrollment_total": 119,
            "class_number": 5987,
            "start_time": "15:30",
            "subject": "MATH"
        },
        {
            "building": "DWE",
            "term": 1159,
            "last_updated": "2015-08-19T22:06:41-04:00",
            "catalog_number": "115",
            "end_date": "10/12",
            "title": "Linear Algebra for Engineering",
            "section": "LEC 002",
            "instructors": [],
            "weekdays": "M",
            "start_date": "10/12",
            "room": "1501",
            "end_time": "16:20",
            "enrollment_total": 119,
            "class_number": 5987,
            "start_time": "15:30",
            "subject": "MATH"
        },
        {
            "building": "DWE",
            "term": 1159,
            "last_updated": "2015-08-19T22:06:41-04:00",
            "catalog_number": "115",
            "end_date": "10/26",
            "title": "Linear Algebra for Engineering",
            "section": "LEC 002",
            "instructors": [],
            "weekdays": "M",
            "start_date": "10/26",
            "room": "1501",
            "end_time": "16:20",
            "enrollment_total": 119,
            "class_number": 5987,
            "start_time": "15:30",
            "subject": "MATH"
        },
        {
            "building": "DWE",
            "term": 1159,
            "last_updated": "2015-08-19T22:06:41-04:00",
            "catalog_number": "115",
            "end_date": "11/09",
            "title": "Linear Algebra for Engineering",
            "section": "LEC 002",
            "instructors": [],
            "weekdays": "M",
            "start_date": "11/09",
            "room": "1501",
            "end_time": "16:20",
            "enrollment_total": 119,
            "class_number": 5987,
            "start_time": "15:30",
            "subject": "MATH"
        },
        {
            "building": "DWE",
            "term": 1159,
            "last_updated": "2015-08-19T22:06:41-04:00",
            "catalog_number": "115",
            "end_date": "11/23",
            "title": "Linear Algebra for Engineering",
            "section": "LEC 002",
            "instructors": [],
            "weekdays": "M",
            "start_date": "11/23",
            "room": "1501",
            "end_time": "16:20",
            "enrollment_total": 119,
            "class_number": 5987,
            "start_time": "15:30",
            "subject": "MATH"
        },
        {
            "building": "DWE",
            "term": 1159,
            "last_updated": "2015-08-19T22:06:41-04:00",
            "catalog_number": "115",
            "end_date": null,
            "title": "Linear Algebra for Engineering",
            "section": "LEC 003",
            "instructors": [],
            "weekdays": "M",
            "start_date": null,
            "room": "1501",
            "end_time": "09:20",
            "enrollment_total": 118,
            "class_number": 5988,
            "start_time": "08:30",
            "subject": "MATH"
        },
        {
            "building": "DWE",
            "term": 1159,
            "last_updated": "2015-08-19T22:06:41-04:00",
            "catalog_number": "115",
            "end_date": null,
            "title": "Linear Algebra for Engineering",
            "section": "LEC 003",
            "instructors": [],
            "weekdays": "T",
            "start_date": null,
            "room": "1501",
            "end_time": "09:20",
            "enrollment_total": 118,
            "class_number": 5988,
            "start_time": "08:30",
            "subject": "MATH"
        },
        {
            "building": "DWE",
            "term": 1159,
            "last_updated": "2015-08-19T22:06:41-04:00",
            "catalog_number": "115",
            "end_date": null,
            "title": "Linear Algebra for Engineering",
            "section": "LEC 003",
            "instructors": [],
            "weekdays": "F",
            "start_date": null,
            "room": "1501",
            "end_time": "09:20",
            "enrollment_total": 118,
            "class_number": 5988,
            "start_time": "08:30",
            "subject": "MATH"
        },
        {
            "building": "DWE",
            "term": 1159,
            "last_updated": "2015-08-19T22:06:41-04:00",
            "catalog_number": "115",
            "end_date": "10/02",
            "title": "Linear Algebra for Engineering",
            "section": "LEC 003",
            "instructors": [],
            "weekdays": "F",
            "start_date": "10/02",
            "room": "1501",
            "end_time": "10:20",
            "enrollment_total": 118,
            "class_number": 5988,
            "start_time": "09:30",
            "subject": "MATH"
        },
        {
            "building": "DWE",
            "term": 1159,
            "last_updated": "2015-08-19T22:06:41-04:00",
            "catalog_number": "115",
            "end_date": "10/16",
            "title": "Linear Algebra for Engineering",
            "section": "LEC 003",
            "instructors": [],
            "weekdays": "F",
            "start_date": "10/16",
            "room": "1501",
            "end_time": "10:20",
            "enrollment_total": 118,
            "class_number": 5988,
            "start_time": "09:30",
            "subject": "MATH"
        },
        {
            "building": "DWE",
            "term": 1159,
            "last_updated": "2015-08-19T22:06:41-04:00",
            "catalog_number": "115",
            "end_date": "10/30",
            "title": "Linear Algebra for Engineering",
            "section": "LEC 003",
            "instructors": [],
            "weekdays": "F",
            "start_date": "10/30",
            "room": "1501",
            "end_time": "10:20",
            "enrollment_total": 118,
            "class_number": 5988,
            "start_time": "09:30",
            "subject": "MATH"
        },
        {
            "building": "DWE",
            "term": 1159,
            "last_updated": "2015-08-19T22:06:41-04:00",
            "catalog_number": "115",
            "end_date": "11/13",
            "title": "Linear Algebra for Engineering",
            "section": "LEC 003",
            "instructors": [],
            "weekdays": "F",
            "start_date": "11/13",
            "room": "1501",
            "end_time": "10:20",
            "enrollment_total": 118,
            "class_number": 5988,
            "start_time": "09:30",
            "subject": "MATH"
        },
        {
            "building": "DWE",
            "term": 1159,
            "last_updated": "2015-08-19T22:06:41-04:00",
            "catalog_number": "115",
            "end_date": "11/27",
            "title": "Linear Algebra for Engineering",
            "section": "LEC 003",
            "instructors": [],
            "weekdays": "F",
            "start_date": "11/27",
            "room": "1501",
            "end_time": "10:20",
            "enrollment_total": 118,
            "class_number": 5988,
            "start_time": "09:30",
            "subject": "MATH"
        },
        {
            "building": "DWE",
            "term": 1159,
            "last_updated": "2015-08-19T22:06:41-04:00",
            "catalog_number": "116",
            "end_date": null,
            "title": "Calculus 1 for Engineering",
            "section": "LEC 004",
            "instructors": [
                "Girelli,Florian"
            ],
            "weekdays": "MWF",
            "start_date": null,
            "room": "1501",
            "end_time": "14:20",
            "enrollment_total": 119,
            "class_number": 6168,
            "start_time": "13:30",
            "subject": "MATH"
        },
        {
            "building": "DWE",
            "term": 1159,
            "last_updated": "2015-08-19T22:06:41-04:00",
            "catalog_number": "116",
            "end_date": "10/02",
            "title": "Calculus 1 for Engineering",
            "section": "LEC 004",
            "instructors": [
                "Girelli,Florian"
            ],
            "weekdays": "F",
            "start_date": "10/02",
            "room": "1501",
            "end_time": "16:20",
            "enrollment_total": 119,
            "class_number": 6168,
            "start_time": "15:30",
            "subject": "MATH"
        },
        {
            "building": "DWE",
            "term": 1159,
            "last_updated": "2015-08-19T22:06:41-04:00",
            "catalog_number": "116",
            "end_date": "10/16",
            "title": "Calculus 1 for Engineering",
            "section": "LEC 004",
            "instructors": [
                "Girelli,Florian"
            ],
            "weekdays": "F",
            "start_date": "10/16",
            "room": "1501",
            "end_time": "16:20",
            "enrollment_total": 119,
            "class_number": 6168,
            "start_time": "15:30",
            "subject": "MATH"
        },
        {
            "building": "DWE",
            "term": 1159,
            "last_updated": "2015-08-19T22:06:41-04:00",
            "catalog_number": "116",
            "end_date": "10/30",
            "title": "Calculus 1 for Engineering",
            "section": "LEC 004",
            "instructors": [
                "Girelli,Florian"
            ],
            "weekdays": "F",
            "start_date": "10/30",
            "room": "1501",
            "end_time": "16:20",
            "enrollment_total": 119,
            "class_number": 6168,
            "start_time": "15:30",
            "subject": "MATH"
        },
        {
            "building": "DWE",
            "term": 1159,
            "last_updated": "2015-08-19T22:06:41-04:00",
            "catalog_number": "116",
            "end_date": "11/13",
            "title": "Calculus 1 for Engineering",
            "section": "LEC 004",
            "instructors": [
                "Girelli,Florian"
            ],
            "weekdays": "F",
            "start_date": "11/13",
            "room": "1501",
            "end_time": "16:20",
            "enrollment_total": 119,
            "class_number": 6168,
            "start_time": "15:30",
            "subject": "MATH"
        },
        {
            "building": "DWE",
            "term": 1159,
            "last_updated": "2015-08-19T22:06:41-04:00",
            "catalog_number": "116",
            "end_date": "11/27",
            "title": "Calculus 1 for Engineering",
            "section": "LEC 004",
            "instructors": [
                "Girelli,Florian"
            ],
            "weekdays": "F",
            "start_date": "11/27",
            "room": "1501",
            "end_time": "16:20",
            "enrollment_total": 119,
            "class_number": 6168,
            "start_time": "15:30",
            "subject": "MATH"
        },
        {
            "building": "DWE",
            "term": 1159,
            "last_updated": "2015-08-19T22:06:41-04:00",
            "catalog_number": "116",
            "end_date": null,
            "title": "Calculus 1 for Engineering",
            "section": "LEC 005",
            "instructors": [
                "Girelli,Florian"
            ],
            "weekdays": "MWF",
            "start_date": null,
            "room": "1501",
            "end_time": "11:20",
            "enrollment_total": 116,
            "class_number": 6169,
            "start_time": "10:30",
            "subject": "MATH"
        },
        {
            "building": "DWE",
            "term": 1159,
            "last_updated": "2015-08-19T22:06:41-04:00",
            "catalog_number": "127",
            "end_date": null,
            "title": "Calculus 1 for the Sciences",
            "section": "TUT 101",
            "instructors": [],
            "weekdays": "M",
            "start_date": null,
            "room": "1501",
            "end_time": "18:50",
            "enrollment_total": 117,
            "class_number": 6088,
            "start_time": "17:30",
            "subject": "MATH"
        },
        {
            "building": "DWE",
            "term": 1159,
            "last_updated": "2015-08-19T22:06:46-04:00",
            "catalog_number": "100",
            "end_date": null,
            "title": "Introduction to Mechanical Engineering Practice 1",
            "section": "LEC 001",
            "instructors": [
                "Baleshta,James Robert"
            ],
            "weekdays": "Th",
            "start_date": null,
            "room": "1501",
            "end_time": "13:20",
            "enrollment_total": 120,
            "class_number": 4845,
            "start_time": "12:30",
            "subject": "ME"
        },
        {
            "building": "DWE",
            "term": 1159,
            "last_updated": "2015-08-19T22:06:46-04:00",
            "catalog_number": "100",
            "end_date": "09/25",
            "title": "Introduction to Mechanical Engineering Practice 1",
            "section": "LEC 001",
            "instructors": [
                "Trivett,Andrew"
            ],
            "weekdays": "F",
            "start_date": "09/25",
            "room": "1501",
            "end_time": "16:20",
            "enrollment_total": 120,
            "class_number": 4845,
            "start_time": "15:30",
            "subject": "ME"
        },
        {
            "building": "DWE",
            "term": 1159,
            "last_updated": "2015-08-19T22:06:46-04:00",
            "catalog_number": "100",
            "end_date": "10/09",
            "title": "Introduction to Mechanical Engineering Practice 1",
            "section": "LEC 001",
            "instructors": [
                "Baleshta,James Robert"
            ],
            "weekdays": "F",
            "start_date": "10/09",
            "room": "1501",
            "end_time": "16:20",
            "enrollment_total": 120,
            "class_number": 4845,
            "start_time": "15:30",
            "subject": "ME"
        },
        {
            "building": "DWE",
            "term": 1159,
            "last_updated": "2015-08-19T22:06:46-04:00",
            "catalog_number": "100",
            "end_date": "10/23",
            "title": "Introduction to Mechanical Engineering Practice 1",
            "section": "LEC 001",
            "instructors": [
                "Baleshta,James Robert"
            ],
            "weekdays": "F",
            "start_date": "10/23",
            "room": "1501",
            "end_time": "16:20",
            "enrollment_total": 120,
            "class_number": 4845,
            "start_time": "15:30",
            "subject": "ME"
        },
        {
            "building": "DWE",
            "term": 1159,
            "last_updated": "2015-08-19T22:06:46-04:00",
            "catalog_number": "100",
            "end_date": "11/06",
            "title": "Introduction to Mechanical Engineering Practice 1",
            "section": "LEC 001",
            "instructors": [
                "Trivett,Andrew"
            ],
            "weekdays": "F",
            "start_date": "11/06",
            "room": "1501",
            "end_time": "16:20",
            "enrollment_total": 120,
            "class_number": 4845,
            "start_time": "15:30",
            "subject": "ME"
        },
        {
            "building": "DWE",
            "term": 1159,
            "last_updated": "2015-08-19T22:06:46-04:00",
            "catalog_number": "100",
            "end_date": "11/20",
            "title": "Introduction to Mechanical Engineering Practice 1",
            "section": "LEC 001",
            "instructors": [
                "Baleshta,James Robert"
            ],
            "weekdays": "F",
            "start_date": "11/20",
            "room": "1501",
            "end_time": "16:20",
            "enrollment_total": 120,
            "class_number": 4845,
            "start_time": "15:30",
            "subject": "ME"
        },
        {
            "building": "DWE",
            "term": 1159,
            "last_updated": "2015-08-19T22:06:46-04:00",
            "catalog_number": "100",
            "end_date": "12/04",
            "title": "Introduction to Mechanical Engineering Practice 1",
            "section": "LEC 001",
            "instructors": [
                "Trivett,Andrew",
                "Baleshta,James Robert"
            ],
            "weekdays": "F",
            "start_date": "12/04",
            "room": "1501",
            "end_time": "16:20",
            "enrollment_total": 120,
            "class_number": 4845,
            "start_time": "15:30",
            "subject": "ME"
        },
        {
            "building": "DWE",
            "term": 1159,
            "last_updated": "2015-08-19T22:06:46-04:00",
            "catalog_number": "100",
            "end_date": null,
            "title": "Introduction to Mechanical Engineering Practice 1",
            "section": "LEC 002",
            "instructors": [
                "Baleshta,James Robert"
            ],
            "weekdays": "W",
            "start_date": null,
            "room": "1501",
            "end_time": "10:20",
            "enrollment_total": 118,
            "class_number": 4846,
            "start_time": "08:30",
            "subject": "ME"
        },
        {
            "building": "DWE",
            "term": 1159,
            "last_updated": "2015-08-19T22:06:46-04:00",
            "catalog_number": "100",
            "end_date": null,
            "title": "Introduction to Mechanical Engineering Practice 1",
            "section": "LEC 002",
            "instructors": [
                "Trivett,Andrew"
            ],
            "weekdays": "T",
            "start_date": null,
            "room": "1501",
            "end_time": "11:20",
            "enrollment_total": 118,
            "class_number": 4846,
            "start_time": "10:30",
            "subject": "ME"
        },
        {
            "building": "DWE",
            "term": 1159,
            "last_updated": "2015-08-19T22:06:46-04:00",
            "catalog_number": "100",
            "end_date": "09/22",
            "title": "Introduction to Mechanical Engineering Practice 1",
            "section": "LEC 002",
            "instructors": [
                "Baleshta,James Robert"
            ],
            "weekdays": "T",
            "start_date": "09/22",
            "room": "1501",
            "end_time": "12:20",
            "enrollment_total": 118,
            "class_number": 4846,
            "start_time": "11:30",
            "subject": "ME"
        },
        {
            "building": "DWE",
            "term": 1159,
            "last_updated": "2015-08-19T22:06:46-04:00",
            "catalog_number": "100",
            "end_date": "10/06",
            "title": "Introduction to Mechanical Engineering Practice 1",
            "section": "LEC 002",
            "instructors": [
                "Trivett,Andrew"
            ],
            "weekdays": "T",
            "start_date": "10/06",
            "room": "1501",
            "end_time": "12:20",
            "enrollment_total": 118,
            "class_number": 4846,
            "start_time": "11:30",
            "subject": "ME"
        },
        {
            "building": "DWE",
            "term": 1159,
            "last_updated": "2015-08-19T22:06:46-04:00",
            "catalog_number": "100",
            "end_date": "10/20",
            "title": "Introduction to Mechanical Engineering Practice 1",
            "section": "LEC 002",
            "instructors": [
                "Trivett,Andrew"
            ],
            "weekdays": "T",
            "start_date": "10/20",
            "room": "1501",
            "end_time": "12:20",
            "enrollment_total": 118,
            "class_number": 4846,
            "start_time": "11:30",
            "subject": "ME"
        },
        {
            "building": "DWE",
            "term": 1159,
            "last_updated": "2015-08-19T22:06:46-04:00",
            "catalog_number": "100",
            "end_date": "11/03",
            "title": "Introduction to Mechanical Engineering Practice 1",
            "section": "LEC 002",
            "instructors": [
                "Baleshta,James Robert"
            ],
            "weekdays": "T",
            "start_date": "11/03",
            "room": "1501",
            "end_time": "12:20",
            "enrollment_total": 118,
            "class_number": 4846,
            "start_time": "11:30",
            "subject": "ME"
        },
        {
            "building": "DWE",
            "term": 1159,
            "last_updated": "2015-08-19T22:06:46-04:00",
            "catalog_number": "100",
            "end_date": "11/17",
            "title": "Introduction to Mechanical Engineering Practice 1",
            "section": "LEC 002",
            "instructors": [
                "Baleshta,James Robert"
            ],
            "weekdays": "T",
            "start_date": "11/17",
            "room": "1501",
            "end_time": "12:20",
            "enrollment_total": 118,
            "class_number": 4846,
            "start_time": "11:30",
            "subject": "ME"
        },
        {
            "building": "DWE",
            "term": 1159,
            "last_updated": "2015-08-19T22:06:46-04:00",
            "catalog_number": "100",
            "end_date": "12/01",
            "title": "Introduction to Mechanical Engineering Practice 1",
            "section": "LEC 002",
            "instructors": [
                "Trivett,Andrew",
                "Baleshta,James Robert"
            ],
            "weekdays": "T",
            "start_date": "12/01",
            "room": "1501",
            "end_time": "12:20",
            "enrollment_total": 118,
            "class_number": 4846,
            "start_time": "11:30",
            "subject": "ME"
        },
        {
            "building": "DWE",
            "term": 1159,
            "last_updated": "2015-08-19T22:07:53-04:00",
            "catalog_number": "115",
            "end_date": null,
            "title": "Mechanics",
            "section": "LEC 002",
            "instructors": [
                "Jayasundera,Rohan"
            ],
            "weekdays": "MWF",
            "start_date": null,
            "room": "1501",
            "end_time": "13:20",
            "enrollment_total": 121,
            "class_number": 7010,
            "start_time": "12:30",
            "subject": "PHYS"
        },
        {
            "building": "DWE",
            "term": 1159,
            "last_updated": "2015-08-19T22:07:53-04:00",
            "catalog_number": "115",
            "end_date": "09/24",
            "title": "Mechanics",
            "section": "LEC 002",
            "instructors": [
                "Jayasundera,Rohan"
            ],
            "weekdays": "Th",
            "start_date": "09/24",
            "room": "1501",
            "end_time": "16:20",
            "enrollment_total": 121,
            "class_number": 7010,
            "start_time": "15:30",
            "subject": "PHYS"
        },
        {
            "building": "DWE",
            "term": 1159,
            "last_updated": "2015-08-19T22:07:53-04:00",
            "catalog_number": "115",
            "end_date": "10/08",
            "title": "Mechanics",
            "section": "LEC 002",
            "instructors": [
                "Jayasundera,Rohan"
            ],
            "weekdays": "Th",
            "start_date": "10/08",
            "room": "1501",
            "end_time": "16:20",
            "enrollment_total": 121,
            "class_number": 7010,
            "start_time": "15:30",
            "subject": "PHYS"
        },
        {
            "building": "DWE",
            "term": 1159,
            "last_updated": "2015-08-19T22:07:53-04:00",
            "catalog_number": "115",
            "end_date": "10/22",
            "title": "Mechanics",
            "section": "LEC 002",
            "instructors": [
                "Jayasundera,Rohan"
            ],
            "weekdays": "Th",
            "start_date": "10/22",
            "room": "1501",
            "end_time": "16:20",
            "enrollment_total": 121,
            "class_number": 7010,
            "start_time": "15:30",
            "subject": "PHYS"
        },
        {
            "building": "DWE",
            "term": 1159,
            "last_updated": "2015-08-19T22:07:53-04:00",
            "catalog_number": "115",
            "end_date": "11/05",
            "title": "Mechanics",
            "section": "LEC 002",
            "instructors": [
                "Jayasundera,Rohan"
            ],
            "weekdays": "Th",
            "start_date": "11/05",
            "room": "1501",
            "end_time": "16:20",
            "enrollment_total": 121,
            "class_number": 7010,
            "start_time": "15:30",
            "subject": "PHYS"
        },
        {
            "building": "DWE",
            "term": 1159,
            "last_updated": "2015-08-19T22:07:53-04:00",
            "catalog_number": "115",
            "end_date": "11/19",
            "title": "Mechanics",
            "section": "LEC 002",
            "instructors": [
                "Jayasundera,Rohan"
            ],
            "weekdays": "Th",
            "start_date": "11/19",
            "room": "1501",
            "end_time": "16:20",
            "enrollment_total": 121,
            "class_number": 7010,
            "start_time": "15:30",
            "subject": "PHYS"
        },
        {
            "building": "DWE",
            "term": 1159,
            "last_updated": "2015-08-19T22:07:53-04:00",
            "catalog_number": "115",
            "end_date": "12/03",
            "title": "Mechanics",
            "section": "LEC 002",
            "instructors": [
                "Jayasundera,Rohan"
            ],
            "weekdays": "Th",
            "start_date": "12/03",
            "room": "1501",
            "end_time": "16:20",
            "enrollment_total": 121,
            "class_number": 7010,
            "start_time": "15:30",
            "subject": "PHYS"
        },
        {
            "building": "DWE",
            "term": 1159,
            "last_updated": "2015-08-19T22:07:53-04:00",
            "catalog_number": "115",
            "end_date": null,
            "title": "Mechanics",
            "section": "LEC 003",
            "instructors": [
                "Jayasundera,Rohan"
            ],
            "weekdays": "MWF",
            "start_date": null,
            "room": "1501",
            "end_time": "12:20",
            "enrollment_total": 117,
            "class_number": 7011,
            "start_time": "11:30",
            "subject": "PHYS"
        },
        {
            "building": "DWE",
            "term": 1159,
            "last_updated": "2015-08-19T22:07:53-04:00",
            "catalog_number": "115",
            "end_date": "09/24",
            "title": "Mechanics",
            "section": "LEC 003",
            "instructors": [
                "Jayasundera,Rohan"
            ],
            "weekdays": "Th",
            "start_date": "09/24",
            "room": "1501",
            "end_time": "12:20",
            "enrollment_total": 117,
            "class_number": 7011,
            "start_time": "11:30",
            "subject": "PHYS"
        },
        {
            "building": "DWE",
            "term": 1159,
            "last_updated": "2015-08-19T22:07:53-04:00",
            "catalog_number": "115",
            "end_date": "10/08",
            "title": "Mechanics",
            "section": "LEC 003",
            "instructors": [
                "Jayasundera,Rohan"
            ],
            "weekdays": "Th",
            "start_date": "10/08",
            "room": "1501",
            "end_time": "12:20",
            "enrollment_total": 117,
            "class_number": 7011,
            "start_time": "11:30",
            "subject": "PHYS"
        },
        {
            "building": "DWE",
            "term": 1159,
            "last_updated": "2015-08-19T22:07:53-04:00",
            "catalog_number": "115",
            "end_date": "10/22",
            "title": "Mechanics",
            "section": "LEC 003",
            "instructors": [
                "Jayasundera,Rohan"
            ],
            "weekdays": "Th",
            "start_date": "10/22",
            "room": "1501",
            "end_time": "12:20",
            "enrollment_total": 117,
            "class_number": 7011,
            "start_time": "11:30",
            "subject": "PHYS"
        },
        {
            "building": "DWE",
            "term": 1159,
            "last_updated": "2015-08-19T22:07:53-04:00",
            "catalog_number": "115",
            "end_date": "11/05",
            "title": "Mechanics",
            "section": "LEC 003",
            "instructors": [
                "Jayasundera,Rohan"
            ],
            "weekdays": "Th",
            "start_date": "11/05",
            "room": "1501",
            "end_time": "12:20",
            "enrollment_total": 117,
            "class_number": 7011,
            "start_time": "11:30",
            "subject": "PHYS"
        },
        {
            "building": "DWE",
            "term": 1159,
            "last_updated": "2015-08-19T22:07:53-04:00",
            "catalog_number": "115",
            "end_date": "11/19",
            "title": "Mechanics",
            "section": "LEC 003",
            "instructors": [
                "Jayasundera,Rohan"
            ],
            "weekdays": "Th",
            "start_date": "11/19",
            "room": "1501",
            "end_time": "12:20",
            "enrollment_total": 117,
            "class_number": 7011,
            "start_time": "11:30",
            "subject": "PHYS"
        },
        {
            "building": "DWE",
            "term": 1159,
            "last_updated": "2015-08-19T22:07:53-04:00",
            "catalog_number": "115",
            "end_date": "12/03",
            "title": "Mechanics",
            "section": "LEC 003",
            "instructors": [
                "Jayasundera,Rohan"
            ],
            "weekdays": "Th",
            "start_date": "12/03",
            "room": "1501",
            "end_time": "12:20",
            "enrollment_total": 117,
            "class_number": 7011,
            "start_time": "11:30",
            "subject": "PHYS"
        }
    ]
}