{
    "data": [
        {
            "building": "HH",
            "catalog_number": "272",
            "class_number": 2332,
            "end_date": null,
            "end_time": "11:20",
            "enrollment_total": 35,
            "instructors": [
                "Hayes,Frank"
            ],
            "last_updated": "2015-05-04T16:00:07-04:00",
            "room": "1108",
            "section": "LEC 001",
            "start_date": null,
            "start_time": "10:00",
            "subject": "AFM",
            "term": 1155,
            "title": "Corporate Finance 1",
            "weekdays": "TTh"
        },
        {
            "building": "HH",
            "catalog_number": "272",
            "class_number": 2389,
            "end_date": null,
            "end_time": "12:50",
            "enrollment_total": 35,
            "instructors": [
                "Hayes,Frank"
            ],
            "last_updated": "2015-05-04T16:00:07-04:00",
            "room": "1108",
            "section": "LEC 002",
            "start_date": null,
            "start_time": "11:30",
            "subject": "AFM",
            "term": 1155,
            "title": "Corporate Finance 1",
            "weekdays": "TTh"
        },
        {
            "building": "HH",
            "catalog_number": "280",
            "class_number": 2494,
            "end_date": null,
            "end_time": "17:20",
            "enrollment_total": 59,
            "instructors": [
                "Michela,John"
            ],
            "last_updated": "2015-05-04T16:00:08-04:00",
            "room": "1108",
            "section": "LEC 004",
            "start_date": null,
            "start_time": "16:00",
            "subject": "AFM",
            "term": 1155,
            "title": "Introduction to Organizational Behaviour",
            "weekdays": "MW"
        },
        {
            "building": "HH",
            "catalog_number": "280",
            "class_number": 2662,
            "end_date": null,
            "end_time": "18:50",
            "enrollment_total": 41,
            "instructors": [
                "Michela,John"
            ],
            "last_updated": "2015-05-04T16:00:08-04:00",
            "room": "1108",
            "section": "LEC 005",
            "start_date": null,
            "start_time": "17:30",
            "subject": "AFM",
            "term": 1155,
            "title": "Introduction to Organizational Behaviour",
            "weekdays": "MW"
        },
        {
            "building": "HH",
            "catalog_number": "311",
            "class_number": 2609,
            "end_date": null,
            "end_time": "13:50",
            "enrollment_total": 40,
            "instructors": [
                "Fiolleau,Krista"
            ],
            "last_updated": "2015-05-04T16:00:08-04:00",
            "room": "1108",
            "section": "TUT 102",
            "start_date": null,
            "start_time": "12:00",
            "subject": "AFM",
            "term": 1155,
            "title": "Connections to Ethical Context",
            "weekdays": "M"
        },
        {
            "building": "HH",
            "catalog_number": "311",
            "class_number": 2610,
            "end_date": null,
            "end_time": "15:50",
            "enrollment_total": 40,
            "instructors": [
                "Charters,Darren"
            ],
            "last_updated": "2015-05-04T16:00:08-04:00",
            "room": "1108",
            "section": "TUT 103",
            "start_date": null,
            "start_time": "14:00",
            "subject": "AFM",
            "term": 1155,
            "title": "Connections to Ethical Context",
            "weekdays": "M"
        },
        {
            "building": "HH",
            "catalog_number": "351",
            "class_number": 2619,
            "end_date": null,
            "end_time": "09:50",
            "enrollment_total": 57,
            "instructors": [
                "Robinson,Linda A."
            ],
            "last_updated": "2015-05-04T16:00:10-04:00",
            "room": "1108",
            "section": "LEC 003",
            "start_date": null,
            "start_time": "08:30",
            "subject": "AFM",
            "term": 1155,
            "title": "Audit Strategy",
            "weekdays": "TTh"
        },
        {
            "building": "HH",
            "catalog_number": "363",
            "class_number": 2626,
            "end_date": null,
            "end_time": "14:20",
            "enrollment_total": 57,
            "instructors": [
                "Rogozynski,Daniel John"
            ],
            "last_updated": "2015-05-04T16:00:11-04:00",
            "room": "1108",
            "section": "LEC 003",
            "start_date": null,
            "start_time": "13:00",
            "subject": "AFM",
            "term": 1155,
            "title": "Taxation 2 for Accountants",
            "weekdays": "TTh"
        },
        {
            "building": "HH",
            "catalog_number": "363",
            "class_number": 2627,
            "end_date": null,
            "end_time": "15:50",
            "enrollment_total": 58,
            "instructors": [
                "Rogozynski,Daniel John"
            ],
            "last_updated": "2015-05-04T16:00:11-04:00",
            "room": "1108",
            "section": "LEC 004",
            "start_date": null,
            "start_time": "14:30",
            "subject": "AFM",
            "term": 1155,
            "title": "Taxation 2 for Accountants",
            "weekdays": "TTh"
        },
        {
            "building": "HH",
            "catalog_number": "363",
            "class_number": 4880,
            "end_date": null,
            "end_time": "17:20",
            "enrollment_total": 56,
            "instructors": [
                "Rogozynski,Daniel John"
            ],
            "last_updated": "2015-05-04T16:00:11-04:00",
            "room": "1108",
            "section": "LEC 005",
            "start_date": null,
            "start_time": "16:00",
            "subject": "AFM",
            "term": 1155,
            "title": "Taxation 2 for Accountants",
            "weekdays": "TTh"
        },
        {
            "building": "HH",
            "catalog_number": "492",
            "class_number": 2390,
            "end_date": null,
            "end_time": "15:50",
            "enrollment_total": 10,
            "instructors": [
                "Chen,Changling"
            ],
            "last_updated": "2015-05-04T16:00:14-04:00",
            "room": "1108",
            "section": "LEC 001",
            "start_date": null,
            "start_time": "13:00",
            "subject": "AFM",
            "term": 1155,
            "title": "Financial Statement Analysis",
            "weekdays": "W"
        },
        {
            "building": "HH",
            "catalog_number": "610",
            "class_number": 4946,
            "end_date": null,
            "end_time": "13:50",
            "enrollment_total": 31,
            "instructors": [],
            "last_updated": "2015-05-04T16:02:30-04:00",
            "room": "1108",
            "section": "TUT 105",
            "start_date": null,
            "start_time": "09:00",
            "subject": "ACC",
            "term": 1155,
            "title": "Public Accounting Practice",
            "weekdays": "F"
        }
    ]
}