{
    "data": [
        {
            "building": "ML",
            "catalog_number": "152",
            "class_number": 2226,
            "end_date": null,
            "end_time": "17:20",
            "enrollment_total": 17,
            "instructors": [
                "Pirie,Nathan Adam Martin"
            ],
            "last_updated": "2015-05-04T16:01:17-04:00",
            "room": "349",
            "section": "LEC 001",
            "start_date": null,
            "start_time": "16:00",
            "subject": "FR",
            "term": 1155,
            "title": "Basic French 2",
            "weekdays": "TTh"
        },
        {
            "building": "ML",
            "catalog_number": "486",
            "class_number": 4950,
            "end_date": null,
            "end_time": "11:20",
            "enrollment_total": 12,
            "instructors": [
                "Penate,Rocky"
            ],
            "last_updated": "2015-05-04T16:01:18-04:00",
            "room": "349",
            "section": "LEC 001",
            "start_date": null,
            "start_time": "10:00",
            "subject": "FR",
            "term": 1155,
            "title": "Topics in French Cultural Studies",
            "weekdays": "MTh"
        }
    ]
}