{
    "data": [
        {
            "building": "PHR",
            "term": 1159,
            "last_updated": "2015-08-19T22:07:37-04:00",
            "catalog_number": "220",
            "end_date": "10/23",
            "title": "Integrated Patient Focused Care 1",
            "section": "LEC 001",
            "instructors": [
                "Chang,Feng"
            ],
            "weekdays": "M",
            "start_date": "09/14",
            "room": "1004",
            "end_time": "11:20",
            "enrollment_total": 120,
            "class_number": 7448,
            "start_time": "08:30",
            "subject": "PHARM"
        },
        {
            "building": "PHR",
            "term": 1159,
            "last_updated": "2015-08-19T22:07:37-04:00",
            "catalog_number": "220",
            "end_date": "10/23",
            "title": "Integrated Patient Focused Care 1",
            "section": "LEC 001",
            "instructors": [
                "Chang,Feng"
            ],
            "weekdays": "T",
            "start_date": "09/14",
            "room": "1004",
            "end_time": "14:20",
            "enrollment_total": 120,
            "class_number": 7448,
            "start_time": "11:30",
            "subject": "PHARM"
        },
        {
            "building": "PHR",
            "term": 1159,
            "last_updated": "2015-08-19T22:07:37-04:00",
            "catalog_number": "220",
            "end_date": "10/23",
            "title": "Integrated Patient Focused Care 1",
            "section": "LEC 001",
            "instructors": [
                "Chang,Feng"
            ],
            "weekdays": "Th",
            "start_date": "09/14",
            "room": "1004",
            "end_time": "12:20",
            "enrollment_total": 120,
            "class_number": 7448,
            "start_time": "10:30",
            "subject": "PHARM"
        },
        {
            "building": "PHR",
            "term": 1159,
            "last_updated": "2015-08-19T22:07:37-04:00",
            "catalog_number": "220",
            "end_date": "10/23",
            "title": "Integrated Patient Focused Care 1",
            "section": "TUT 101",
            "instructors": [
                "Chang,Feng"
            ],
            "weekdays": "F",
            "start_date": "09/14",
            "room": "1004",
            "end_time": "10:20",
            "enrollment_total": 120,
            "class_number": 8180,
            "start_time": "08:30",
            "subject": "PHARM"
        },
        {
            "building": "PHR",
            "term": 1159,
            "last_updated": "2015-08-19T22:07:38-04:00",
            "catalog_number": "221",
            "end_date": "12/04",
            "title": "Integrated Patient Focused Care 2",
            "section": "LEC 001",
            "instructors": [
                "Barrett,Brett"
            ],
            "weekdays": "M",
            "start_date": "10/26",
            "room": "1004",
            "end_time": "11:20",
            "enrollment_total": 123,
            "class_number": 7449,
            "start_time": "08:30",
            "subject": "PHARM"
        },
        {
            "building": "PHR",
            "term": 1159,
            "last_updated": "2015-08-19T22:07:38-04:00",
            "catalog_number": "221",
            "end_date": "12/04",
            "title": "Integrated Patient Focused Care 2",
            "section": "LEC 001",
            "instructors": [
                "Barrett,Brett"
            ],
            "weekdays": "T",
            "start_date": "10/26",
            "room": "1004",
            "end_time": "14:20",
            "enrollment_total": 123,
            "class_number": 7449,
            "start_time": "11:30",
            "subject": "PHARM"
        },
        {
            "building": "PHR",
            "term": 1159,
            "last_updated": "2015-08-19T22:07:38-04:00",
            "catalog_number": "221",
            "end_date": "12/04",
            "title": "Integrated Patient Focused Care 2",
            "section": "LEC 001",
            "instructors": [
                "Barrett,Brett"
            ],
            "weekdays": "Th",
            "start_date": "10/26",
            "room": "1004",
            "end_time": "12:20",
            "enrollment_total": 123,
            "class_number": 7449,
            "start_time": "10:30",
            "subject": "PHARM"
        },
        {
            "building": "PHR",
            "term": 1159,
            "last_updated": "2015-08-19T22:07:38-04:00",
            "catalog_number": "221",
            "end_date": "12/04",
            "title": "Integrated Patient Focused Care 2",
            "section": "TUT 101",
            "instructors": [
                "Barrett,Brett"
            ],
            "weekdays": "F",
            "start_date": "10/26",
            "room": "1004",
            "end_time": "10:20",
            "enrollment_total": 123,
            "class_number": 8181,
            "start_time": "08:30",
            "subject": "PHARM"
        },
        {
            "building": "PHR",
            "term": 1159,
            "last_updated": "2015-08-19T22:07:38-04:00",
            "catalog_number": "224",
            "end_date": null,
            "title": "Pharmacokinetic Fundamentals",
            "section": "LEC 001",
            "instructors": [
                "Edginton,Andrea"
            ],
            "weekdays": "Th",
            "start_date": null,
            "room": "1004",
            "end_time": "16:50",
            "enrollment_total": 120,
            "class_number": 7450,
            "start_time": "14:30",
            "subject": "PHARM"
        },
        {
            "building": "PHR",
            "term": 1159,
            "last_updated": "2015-08-19T22:07:38-04:00",
            "catalog_number": "224",
            "end_date": null,
            "title": "Pharmacokinetic Fundamentals",
            "section": "TUT 101",
            "instructors": [
                "Edginton,Andrea"
            ],
            "weekdays": "M",
            "start_date": null,
            "room": "1004",
            "end_time": "13:50",
            "enrollment_total": 120,
            "class_number": 7469,
            "start_time": "12:30",
            "subject": "PHARM"
        },
        {
            "building": "PHR",
            "term": 1159,
            "last_updated": "2015-08-19T22:07:38-04:00",
            "catalog_number": "227",
            "end_date": null,
            "title": "Health Systems in Society",
            "section": "LEC 001",
            "instructors": [
                "Alsabbagh,Wasem"
            ],
            "weekdays": "T",
            "start_date": null,
            "room": "1004",
            "end_time": "10:20",
            "enrollment_total": 120,
            "class_number": 7451,
            "start_time": "08:30",
            "subject": "PHARM"
        },
        {
            "building": "PHR",
            "term": 1159,
            "last_updated": "2015-08-19T22:07:39-04:00",
            "catalog_number": "232",
            "end_date": null,
            "title": "Medical Microbiology",
            "section": "LEC 001",
            "instructors": [
                "Wasfi,Olla"
            ],
            "weekdays": "M",
            "start_date": null,
            "room": "1004",
            "end_time": "18:20",
            "enrollment_total": 120,
            "class_number": 8182,
            "start_time": "17:30",
            "subject": "PHARM"
        },
        {
            "building": "PHR",
            "term": 1159,
            "last_updated": "2015-08-19T22:07:39-04:00",
            "catalog_number": "366",
            "end_date": null,
            "title": "Concepts in Nutritional Sciences",
            "section": "LEC 001",
            "instructors": [
                "Richard,Cynthia"
            ],
            "weekdays": "F",
            "start_date": null,
            "room": "1004",
            "end_time": "13:20",
            "enrollment_total": 16,
            "class_number": 7495,
            "start_time": "10:30",
            "subject": "PHARM"
        },
        {
            "building": "PHR",
            "term": 1159,
            "last_updated": "2015-08-19T22:07:41-04:00",
            "catalog_number": "420",
            "end_date": "10/23",
            "title": "Integrated Patient Focused Care 7",
            "section": "LEC 001",
            "instructors": [
                "Patel,Tejal"
            ],
            "weekdays": "W",
            "start_date": "09/14",
            "room": "1004",
            "end_time": "10:20",
            "enrollment_total": 118,
            "class_number": 7454,
            "start_time": "08:30",
            "subject": "PHARM"
        },
        {
            "building": "PHR",
            "term": 1159,
            "last_updated": "2015-08-19T22:07:41-04:00",
            "catalog_number": "420",
            "end_date": "10/23",
            "title": "Integrated Patient Focused Care 7",
            "section": "TUT 101",
            "instructors": [
                "Patel,Tejal"
            ],
            "weekdays": "Th",
            "start_date": "09/14",
            "room": "1004",
            "end_time": "14:20",
            "enrollment_total": 118,
            "class_number": 7470,
            "start_time": "12:30",
            "subject": "PHARM"
        },
        {
            "building": "PHR",
            "term": 1159,
            "last_updated": "2015-08-19T22:07:41-04:00",
            "catalog_number": "421",
            "end_date": "12/04",
            "title": "Integrated Patient Focused Care 8",
            "section": "LEC 001",
            "instructors": [
                "Beazely,Michael"
            ],
            "weekdays": "W",
            "start_date": "10/26",
            "room": "1004",
            "end_time": "10:20",
            "enrollment_total": 118,
            "class_number": 7455,
            "start_time": "08:30",
            "subject": "PHARM"
        },
        {
            "building": "PHR",
            "term": 1159,
            "last_updated": "2015-08-19T22:07:41-04:00",
            "catalog_number": "421",
            "end_date": "12/04",
            "title": "Integrated Patient Focused Care 8",
            "section": "TUT 101",
            "instructors": [
                "Beazely,Michael"
            ],
            "weekdays": "Th",
            "start_date": "10/26",
            "room": "1004",
            "end_time": "14:20",
            "enrollment_total": 118,
            "class_number": 7471,
            "start_time": "12:30",
            "subject": "PHARM"
        },
        {
            "building": "PHR",
            "term": 1159,
            "last_updated": "2015-08-19T22:07:41-04:00",
            "catalog_number": "428",
            "end_date": null,
            "title": "Professional Practice 4",
            "section": "LEC 001",
            "instructors": [
                "Grindrod,Kelly"
            ],
            "weekdays": "W",
            "start_date": null,
            "room": "1004",
            "end_time": "13:20",
            "enrollment_total": 117,
            "class_number": 7456,
            "start_time": "11:30",
            "subject": "PHARM"
        },
        {
            "building": "PHR",
            "term": 1159,
            "last_updated": "2015-08-19T22:07:42-04:00",
            "catalog_number": "490",
            "end_date": null,
            "title": "Seminars in Pharmacy 2",
            "section": "SEM 001",
            "instructors": [
                "Grindrod,Kelly"
            ],
            "weekdays": "W",
            "start_date": null,
            "room": "1004",
            "end_time": "14:20",
            "enrollment_total": 117,
            "class_number": 7457,
            "start_time": "13:30",
            "subject": "PHARM"
        }
    ]
}