{
    "data": [
        {
            "building": "RCH",
            "term": 1159,
            "last_updated": "2015-08-19T22:04:32-04:00",
            "catalog_number": "100",
            "end_date": "09/22",
            "title": "Chemical Engineering Concepts 1",
            "section": "LEC 001",
            "instructors": [
                "Moresoli,Christine"
            ],
            "weekdays": "T",
            "start_date": "09/22",
            "room": "301",
            "end_time": "13:20",
            "enrollment_total": 146,
            "class_number": 4755,
            "start_time": "12:30",
            "subject": "CHE"
        },
        {
            "building": "RCH",
            "term": 1159,
            "last_updated": "2015-08-19T22:04:32-04:00",
            "catalog_number": "100",
            "end_date": "10/06",
            "title": "Chemical Engineering Concepts 1",
            "section": "LEC 001",
            "instructors": [
                "Ioannidis,Marios"
            ],
            "weekdays": "T",
            "start_date": "10/06",
            "room": "301",
            "end_time": "13:20",
            "enrollment_total": 146,
            "class_number": 4755,
            "start_time": "12:30",
            "subject": "CHE"
        },
        {
            "building": "RCH",
            "term": 1159,
            "last_updated": "2015-08-19T22:04:32-04:00",
            "catalog_number": "100",
            "end_date": "10/20",
            "title": "Chemical Engineering Concepts 1",
            "section": "LEC 001",
            "instructors": [
                "Moresoli,Christine"
            ],
            "weekdays": "T",
            "start_date": "10/20",
            "room": "301",
            "end_time": "13:20",
            "enrollment_total": 146,
            "class_number": 4755,
            "start_time": "12:30",
            "subject": "CHE"
        },
        {
            "building": "RCH",
            "term": 1159,
            "last_updated": "2015-08-19T22:04:32-04:00",
            "catalog_number": "100",
            "end_date": "11/03",
            "title": "Chemical Engineering Concepts 1",
            "section": "LEC 001",
            "instructors": [
                "Ioannidis,Marios"
            ],
            "weekdays": "T",
            "start_date": "11/03",
            "room": "301",
            "end_time": "13:20",
            "enrollment_total": 146,
            "class_number": 4755,
            "start_time": "12:30",
            "subject": "CHE"
        },
        {
            "building": "RCH",
            "term": 1159,
            "last_updated": "2015-08-19T22:04:32-04:00",
            "catalog_number": "100",
            "end_date": "11/17",
            "title": "Chemical Engineering Concepts 1",
            "section": "LEC 001",
            "instructors": [
                "Moresoli,Christine"
            ],
            "weekdays": "T",
            "start_date": "11/17",
            "room": "301",
            "end_time": "13:20",
            "enrollment_total": 146,
            "class_number": 4755,
            "start_time": "12:30",
            "subject": "CHE"
        },
        {
            "building": "RCH",
            "term": 1159,
            "last_updated": "2015-08-19T22:04:32-04:00",
            "catalog_number": "100",
            "end_date": "12/01",
            "title": "Chemical Engineering Concepts 1",
            "section": "LEC 001",
            "instructors": [
                "Ioannidis,Marios",
                "Moresoli,Christine"
            ],
            "weekdays": "T",
            "start_date": "12/01",
            "room": "301",
            "end_time": "13:20",
            "enrollment_total": 146,
            "class_number": 4755,
            "start_time": "12:30",
            "subject": "CHE"
        },
        {
            "building": "RCH",
            "term": 1159,
            "last_updated": "2015-08-19T22:04:32-04:00",
            "catalog_number": "100",
            "end_date": null,
            "title": "Chemical Engineering Concepts 1",
            "section": "TUT 201",
            "instructors": [
                "Ioannidis,Marios"
            ],
            "weekdays": "M",
            "start_date": null,
            "room": "301",
            "end_time": "14:20",
            "enrollment_total": 49,
            "class_number": 4757,
            "start_time": "13:30",
            "subject": "CHE"
        },
        {
            "building": "RCH",
            "term": 1159,
            "last_updated": "2015-08-19T22:04:32-04:00",
            "catalog_number": "100",
            "end_date": null,
            "title": "Chemical Engineering Concepts 1",
            "section": "TUT 202",
            "instructors": [
                "Ioannidis,Marios"
            ],
            "weekdays": "M",
            "start_date": null,
            "room": "301",
            "end_time": "14:20",
            "enrollment_total": 48,
            "class_number": 4831,
            "start_time": "13:30",
            "subject": "CHE"
        },
        {
            "building": "RCH",
            "term": 1159,
            "last_updated": "2015-08-19T22:04:32-04:00",
            "catalog_number": "100",
            "end_date": null,
            "title": "Chemical Engineering Concepts 1",
            "section": "TUT 203",
            "instructors": [
                "Ioannidis,Marios"
            ],
            "weekdays": "M",
            "start_date": null,
            "room": "301",
            "end_time": "14:20",
            "enrollment_total": 49,
            "class_number": 4832,
            "start_time": "13:30",
            "subject": "CHE"
        },
        {
            "building": "RCH",
            "term": 1159,
            "last_updated": "2015-08-19T22:04:32-04:00",
            "catalog_number": "102",
            "end_date": null,
            "title": "Chemistry for Engineers",
            "section": "LEC 002",
            "instructors": [
                "Boghaert,Eline"
            ],
            "weekdays": "TTh",
            "start_date": null,
            "room": "301",
            "end_time": "09:20",
            "enrollment_total": 125,
            "class_number": 4765,
            "start_time": "08:30",
            "subject": "CHE"
        },
        {
            "building": "RCH",
            "term": 1159,
            "last_updated": "2015-08-19T22:04:32-04:00",
            "catalog_number": "102",
            "end_date": null,
            "title": "Chemistry for Engineers",
            "section": "LEC 002",
            "instructors": [
                "Boghaert,Eline"
            ],
            "weekdays": "W",
            "start_date": null,
            "room": "301",
            "end_time": "10:20",
            "enrollment_total": 125,
            "class_number": 4765,
            "start_time": "09:30",
            "subject": "CHE"
        },
        {
            "building": "RCH",
            "term": 1159,
            "last_updated": "2015-08-19T22:04:32-04:00",
            "catalog_number": "102",
            "end_date": "09/28",
            "title": "Chemistry for Engineers",
            "section": "LEC 002",
            "instructors": [
                "Boghaert,Eline"
            ],
            "weekdays": "M",
            "start_date": "09/28",
            "room": "301",
            "end_time": "11:20",
            "enrollment_total": 125,
            "class_number": 4765,
            "start_time": "10:30",
            "subject": "CHE"
        },
        {
            "building": "RCH",
            "term": 1159,
            "last_updated": "2015-08-19T22:04:32-04:00",
            "catalog_number": "102",
            "end_date": "10/12",
            "title": "Chemistry for Engineers",
            "section": "LEC 002",
            "instructors": [
                "Boghaert,Eline"
            ],
            "weekdays": "M",
            "start_date": "10/12",
            "room": "301",
            "end_time": "11:20",
            "enrollment_total": 125,
            "class_number": 4765,
            "start_time": "10:30",
            "subject": "CHE"
        },
        {
            "building": "RCH",
            "term": 1159,
            "last_updated": "2015-08-19T22:04:32-04:00",
            "catalog_number": "102",
            "end_date": "10/26",
            "title": "Chemistry for Engineers",
            "section": "LEC 002",
            "instructors": [
                "Boghaert,Eline"
            ],
            "weekdays": "M",
            "start_date": "10/26",
            "room": "301",
            "end_time": "11:20",
            "enrollment_total": 125,
            "class_number": 4765,
            "start_time": "10:30",
            "subject": "CHE"
        },
        {
            "building": "RCH",
            "term": 1159,
            "last_updated": "2015-08-19T22:04:32-04:00",
            "catalog_number": "102",
            "end_date": "11/09",
            "title": "Chemistry for Engineers",
            "section": "LEC 002",
            "instructors": [
                "Boghaert,Eline"
            ],
            "weekdays": "M",
            "start_date": "11/09",
            "room": "301",
            "end_time": "11:20",
            "enrollment_total": 125,
            "class_number": 4765,
            "start_time": "10:30",
            "subject": "CHE"
        },
        {
            "building": "RCH",
            "term": 1159,
            "last_updated": "2015-08-19T22:04:32-04:00",
            "catalog_number": "102",
            "end_date": "11/23",
            "title": "Chemistry for Engineers",
            "section": "LEC 002",
            "instructors": [
                "Boghaert,Eline"
            ],
            "weekdays": "M",
            "start_date": "11/23",
            "room": "301",
            "end_time": "11:20",
            "enrollment_total": 125,
            "class_number": 4765,
            "start_time": "10:30",
            "subject": "CHE"
        },
        {
            "building": "RCH",
            "term": 1159,
            "last_updated": "2015-08-19T22:04:32-04:00",
            "catalog_number": "102",
            "end_date": null,
            "title": "Chemistry for Engineers",
            "section": "LEC 006",
            "instructors": [
                "Hassel,Anna-Katharina"
            ],
            "weekdays": "W",
            "start_date": null,
            "room": "301",
            "end_time": "15:20",
            "enrollment_total": 154,
            "class_number": 4784,
            "start_time": "14:30",
            "subject": "CHE"
        },
        {
            "building": "RCH",
            "term": 1159,
            "last_updated": "2015-08-19T22:04:46-04:00",
            "catalog_number": "100",
            "end_date": null,
            "title": "Civil Engineering Concepts",
            "section": "LEC 001",
            "instructors": [
                "McKillop,Robert"
            ],
            "weekdays": "MWF",
            "start_date": null,
            "room": "301",
            "end_time": "09:20",
            "enrollment_total": 126,
            "class_number": 8139,
            "start_time": "08:30",
            "subject": "CIVE"
        },
        {
            "building": "RCH",
            "term": 1159,
            "last_updated": "2015-08-19T22:04:46-04:00",
            "catalog_number": "104",
            "end_date": null,
            "title": "Mechanics 1",
            "section": "LEC 001",
            "instructors": [
                "Brodland,G. Wayne"
            ],
            "weekdays": "T",
            "start_date": null,
            "room": "301",
            "end_time": "10:50",
            "enrollment_total": 126,
            "class_number": 8146,
            "start_time": "09:30",
            "subject": "CIVE"
        },
        {
            "building": "RCH",
            "term": 1159,
            "last_updated": "2015-08-19T22:04:46-04:00",
            "catalog_number": "104",
            "end_date": "10/02",
            "title": "Mechanics 1",
            "section": "LEC 001",
            "instructors": [
                "Brodland,G. Wayne"
            ],
            "weekdays": "F",
            "start_date": "10/02",
            "room": "301",
            "end_time": "11:20",
            "enrollment_total": 126,
            "class_number": 8146,
            "start_time": "10:30",
            "subject": "CIVE"
        },
        {
            "building": "RCH",
            "term": 1159,
            "last_updated": "2015-08-19T22:04:46-04:00",
            "catalog_number": "104",
            "end_date": "10/16",
            "title": "Mechanics 1",
            "section": "LEC 001",
            "instructors": [
                "Brodland,G. Wayne"
            ],
            "weekdays": "F",
            "start_date": "10/16",
            "room": "301",
            "end_time": "11:20",
            "enrollment_total": 126,
            "class_number": 8146,
            "start_time": "10:30",
            "subject": "CIVE"
        },
        {
            "building": "RCH",
            "term": 1159,
            "last_updated": "2015-08-19T22:04:46-04:00",
            "catalog_number": "104",
            "end_date": "10/30",
            "title": "Mechanics 1",
            "section": "LEC 001",
            "instructors": [
                "Brodland,G. Wayne"
            ],
            "weekdays": "F",
            "start_date": "10/30",
            "room": "301",
            "end_time": "11:20",
            "enrollment_total": 126,
            "class_number": 8146,
            "start_time": "10:30",
            "subject": "CIVE"
        },
        {
            "building": "RCH",
            "term": 1159,
            "last_updated": "2015-08-19T22:04:46-04:00",
            "catalog_number": "104",
            "end_date": "11/13",
            "title": "Mechanics 1",
            "section": "LEC 001",
            "instructors": [
                "Brodland,G. Wayne"
            ],
            "weekdays": "F",
            "start_date": "11/13",
            "room": "301",
            "end_time": "11:20",
            "enrollment_total": 126,
            "class_number": 8146,
            "start_time": "10:30",
            "subject": "CIVE"
        },
        {
            "building": "RCH",
            "term": 1159,
            "last_updated": "2015-08-19T22:04:46-04:00",
            "catalog_number": "104",
            "end_date": "11/27",
            "title": "Mechanics 1",
            "section": "LEC 001",
            "instructors": [
                "Brodland,G. Wayne"
            ],
            "weekdays": "F",
            "start_date": "11/27",
            "room": "301",
            "end_time": "11:20",
            "enrollment_total": 126,
            "class_number": 8146,
            "start_time": "10:30",
            "subject": "CIVE"
        },
        {
            "building": "RCH",
            "term": 1159,
            "last_updated": "2015-08-19T22:04:46-04:00",
            "catalog_number": "115",
            "end_date": null,
            "title": "Linear Algebra",
            "section": "LEC 001",
            "instructors": [
                "Brush,David J"
            ],
            "weekdays": "Th",
            "start_date": null,
            "room": "301",
            "end_time": "10:50",
            "enrollment_total": 125,
            "class_number": 8154,
            "start_time": "09:30",
            "subject": "CIVE"
        },
        {
            "building": "RCH",
            "term": 1159,
            "last_updated": "2015-08-19T22:04:46-04:00",
            "catalog_number": "115",
            "end_date": "09/25",
            "title": "Linear Algebra",
            "section": "LEC 001",
            "instructors": [
                "Brush,David J"
            ],
            "weekdays": "F",
            "start_date": "09/25",
            "room": "301",
            "end_time": "11:20",
            "enrollment_total": 125,
            "class_number": 8154,
            "start_time": "10:30",
            "subject": "CIVE"
        },
        {
            "building": "RCH",
            "term": 1159,
            "last_updated": "2015-08-19T22:04:46-04:00",
            "catalog_number": "115",
            "end_date": "10/09",
            "title": "Linear Algebra",
            "section": "LEC 001",
            "instructors": [
                "Brush,David J"
            ],
            "weekdays": "F",
            "start_date": "10/09",
            "room": "301",
            "end_time": "11:20",
            "enrollment_total": 125,
            "class_number": 8154,
            "start_time": "10:30",
            "subject": "CIVE"
        },
        {
            "building": "RCH",
            "term": 1159,
            "last_updated": "2015-08-19T22:04:46-04:00",
            "catalog_number": "115",
            "end_date": "10/23",
            "title": "Linear Algebra",
            "section": "LEC 001",
            "instructors": [
                "Brush,David J"
            ],
            "weekdays": "F",
            "start_date": "10/23",
            "room": "301",
            "end_time": "11:20",
            "enrollment_total": 125,
            "class_number": 8154,
            "start_time": "10:30",
            "subject": "CIVE"
        },
        {
            "building": "RCH",
            "term": 1159,
            "last_updated": "2015-08-19T22:04:46-04:00",
            "catalog_number": "115",
            "end_date": "11/06",
            "title": "Linear Algebra",
            "section": "LEC 001",
            "instructors": [
                "Brush,David J"
            ],
            "weekdays": "F",
            "start_date": "11/06",
            "room": "301",
            "end_time": "11:20",
            "enrollment_total": 125,
            "class_number": 8154,
            "start_time": "10:30",
            "subject": "CIVE"
        },
        {
            "building": "RCH",
            "term": 1159,
            "last_updated": "2015-08-19T22:04:46-04:00",
            "catalog_number": "115",
            "end_date": "11/20",
            "title": "Linear Algebra",
            "section": "LEC 001",
            "instructors": [
                "Brush,David J"
            ],
            "weekdays": "F",
            "start_date": "11/20",
            "room": "301",
            "end_time": "11:20",
            "enrollment_total": 125,
            "class_number": 8154,
            "start_time": "10:30",
            "subject": "CIVE"
        },
        {
            "building": "RCH",
            "term": 1159,
            "last_updated": "2015-08-19T22:04:46-04:00",
            "catalog_number": "115",
            "end_date": "12/04",
            "title": "Linear Algebra",
            "section": "LEC 001",
            "instructors": [
                "Brush,David J"
            ],
            "weekdays": "F",
            "start_date": "12/04",
            "room": "301",
            "end_time": "11:20",
            "enrollment_total": 125,
            "class_number": 8154,
            "start_time": "10:30",
            "subject": "CIVE"
        },
        {
            "building": "RCH",
            "term": 1159,
            "last_updated": "2015-08-19T22:05:09-04:00",
            "catalog_number": "100A",
            "end_date": null,
            "title": "Electrical and Computer Engineering Practice",
            "section": "SEM 003",
            "instructors": [
                "Neale,Adam John"
            ],
            "weekdays": "T",
            "start_date": null,
            "room": "301",
            "end_time": "15:20",
            "enrollment_total": 153,
            "class_number": 5163,
            "start_time": "14:30",
            "subject": "ECE"
        },
        {
            "building": "RCH",
            "term": 1159,
            "last_updated": "2015-08-19T22:05:09-04:00",
            "catalog_number": "100A",
            "end_date": null,
            "title": "Electrical and Computer Engineering Practice",
            "section": "SEM 003",
            "instructors": [
                "Neale,Adam John"
            ],
            "weekdays": "Th",
            "start_date": null,
            "room": "301",
            "end_time": "15:20",
            "enrollment_total": 153,
            "class_number": 5163,
            "start_time": "14:30",
            "subject": "ECE"
        },
        {
            "building": "RCH",
            "term": 1159,
            "last_updated": "2015-08-19T22:05:09-04:00",
            "catalog_number": "140",
            "end_date": null,
            "title": "Linear Circuits",
            "section": "LEC 002",
            "instructors": [
                "Neale,Adam John"
            ],
            "weekdays": "TTh",
            "start_date": null,
            "room": "301",
            "end_time": "14:20",
            "enrollment_total": 158,
            "class_number": 5176,
            "start_time": "13:30",
            "subject": "ECE"
        },
        {
            "building": "RCH",
            "term": 1159,
            "last_updated": "2015-08-19T22:05:09-04:00",
            "catalog_number": "140",
            "end_date": null,
            "title": "Linear Circuits",
            "section": "LEC 003",
            "instructors": [
                "Levine,Peter"
            ],
            "weekdays": "M",
            "start_date": null,
            "room": "301",
            "end_time": "16:20",
            "enrollment_total": 158,
            "class_number": 5177,
            "start_time": "15:30",
            "subject": "ECE"
        },
        {
            "building": "RCH",
            "term": 1159,
            "last_updated": "2015-08-19T22:05:09-04:00",
            "catalog_number": "140",
            "end_date": null,
            "title": "Linear Circuits",
            "section": "LEC 003",
            "instructors": [
                "Levine,Peter"
            ],
            "weekdays": "T",
            "start_date": null,
            "room": "301",
            "end_time": "16:20",
            "enrollment_total": 158,
            "class_number": 5177,
            "start_time": "15:30",
            "subject": "ECE"
        },
        {
            "building": "RCH",
            "term": 1159,
            "last_updated": "2015-08-19T22:05:09-04:00",
            "catalog_number": "140",
            "end_date": null,
            "title": "Linear Circuits",
            "section": "LEC 003",
            "instructors": [
                "Levine,Peter"
            ],
            "weekdays": "Th",
            "start_date": null,
            "room": "301",
            "end_time": "16:20",
            "enrollment_total": 158,
            "class_number": 5177,
            "start_time": "15:30",
            "subject": "ECE"
        },
        {
            "building": "RCH",
            "term": 1159,
            "last_updated": "2015-08-19T22:05:09-04:00",
            "catalog_number": "140",
            "end_date": "09/25",
            "title": "Linear Circuits",
            "section": "LEC 003",
            "instructors": [
                "Levine,Peter"
            ],
            "weekdays": "F",
            "start_date": "09/25",
            "room": "301",
            "end_time": "16:20",
            "enrollment_total": 158,
            "class_number": 5177,
            "start_time": "15:30",
            "subject": "ECE"
        },
        {
            "building": "RCH",
            "term": 1159,
            "last_updated": "2015-08-19T22:05:09-04:00",
            "catalog_number": "140",
            "end_date": "10/09",
            "title": "Linear Circuits",
            "section": "LEC 003",
            "instructors": [
                "Levine,Peter"
            ],
            "weekdays": "F",
            "start_date": "10/09",
            "room": "301",
            "end_time": "16:20",
            "enrollment_total": 158,
            "class_number": 5177,
            "start_time": "15:30",
            "subject": "ECE"
        },
        {
            "building": "RCH",
            "term": 1159,
            "last_updated": "2015-08-19T22:05:09-04:00",
            "catalog_number": "140",
            "end_date": "10/23",
            "title": "Linear Circuits",
            "section": "LEC 003",
            "instructors": [
                "Levine,Peter"
            ],
            "weekdays": "F",
            "start_date": "10/23",
            "room": "301",
            "end_time": "16:20",
            "enrollment_total": 158,
            "class_number": 5177,
            "start_time": "15:30",
            "subject": "ECE"
        },
        {
            "building": "RCH",
            "term": 1159,
            "last_updated": "2015-08-19T22:05:09-04:00",
            "catalog_number": "140",
            "end_date": "11/06",
            "title": "Linear Circuits",
            "section": "LEC 003",
            "instructors": [
                "Levine,Peter"
            ],
            "weekdays": "F",
            "start_date": "11/06",
            "room": "301",
            "end_time": "16:20",
            "enrollment_total": 158,
            "class_number": 5177,
            "start_time": "15:30",
            "subject": "ECE"
        },
        {
            "building": "RCH",
            "term": 1159,
            "last_updated": "2015-08-19T22:05:09-04:00",
            "catalog_number": "140",
            "end_date": "11/20",
            "title": "Linear Circuits",
            "section": "LEC 003",
            "instructors": [
                "Levine,Peter"
            ],
            "weekdays": "F",
            "start_date": "11/20",
            "room": "301",
            "end_time": "16:20",
            "enrollment_total": 158,
            "class_number": 5177,
            "start_time": "15:30",
            "subject": "ECE"
        },
        {
            "building": "RCH",
            "term": 1159,
            "last_updated": "2015-08-19T22:05:09-04:00",
            "catalog_number": "150",
            "end_date": null,
            "title": "Fundamentals of Programming",
            "section": "LEC 003",
            "instructors": [
                "Ward,Paul A S"
            ],
            "weekdays": "Th",
            "start_date": null,
            "room": "301",
            "end_time": "17:20",
            "enrollment_total": 155,
            "class_number": 4841,
            "start_time": "16:30",
            "subject": "ECE"
        },
        {
            "building": "RCH",
            "term": 1159,
            "last_updated": "2015-08-19T22:05:09-04:00",
            "catalog_number": "150",
            "end_date": null,
            "title": "Fundamentals of Programming",
            "section": "LEC 003",
            "instructors": [
                "Ward,Paul A S"
            ],
            "weekdays": "F",
            "start_date": null,
            "room": "301",
            "end_time": "14:20",
            "enrollment_total": 155,
            "class_number": 4841,
            "start_time": "13:30",
            "subject": "ECE"
        },
        {
            "building": "RCH",
            "term": 1159,
            "last_updated": "2015-08-19T22:05:09-04:00",
            "catalog_number": "150",
            "end_date": "10/02",
            "title": "Fundamentals of Programming",
            "section": "LEC 003",
            "instructors": [
                "Ward,Paul A S"
            ],
            "weekdays": "F",
            "start_date": "10/02",
            "room": "301",
            "end_time": "16:20",
            "enrollment_total": 155,
            "class_number": 4841,
            "start_time": "15:30",
            "subject": "ECE"
        },
        {
            "building": "RCH",
            "term": 1159,
            "last_updated": "2015-08-19T22:05:09-04:00",
            "catalog_number": "150",
            "end_date": "10/16",
            "title": "Fundamentals of Programming",
            "section": "LEC 003",
            "instructors": [
                "Ward,Paul A S"
            ],
            "weekdays": "F",
            "start_date": "10/16",
            "room": "301",
            "end_time": "16:20",
            "enrollment_total": 155,
            "class_number": 4841,
            "start_time": "15:30",
            "subject": "ECE"
        },
        {
            "building": "RCH",
            "term": 1159,
            "last_updated": "2015-08-19T22:05:09-04:00",
            "catalog_number": "150",
            "end_date": "10/30",
            "title": "Fundamentals of Programming",
            "section": "LEC 003",
            "instructors": [
                "Ward,Paul A S"
            ],
            "weekdays": "F",
            "start_date": "10/30",
            "room": "301",
            "end_time": "16:20",
            "enrollment_total": 155,
            "class_number": 4841,
            "start_time": "15:30",
            "subject": "ECE"
        },
        {
            "building": "RCH",
            "term": 1159,
            "last_updated": "2015-08-19T22:05:09-04:00",
            "catalog_number": "150",
            "end_date": "11/13",
            "title": "Fundamentals of Programming",
            "section": "LEC 003",
            "instructors": [
                "Ward,Paul A S"
            ],
            "weekdays": "F",
            "start_date": "11/13",
            "room": "301",
            "end_time": "16:20",
            "enrollment_total": 155,
            "class_number": 4841,
            "start_time": "15:30",
            "subject": "ECE"
        },
        {
            "building": "RCH",
            "term": 1159,
            "last_updated": "2015-08-19T22:05:09-04:00",
            "catalog_number": "150",
            "end_date": "11/27",
            "title": "Fundamentals of Programming",
            "section": "LEC 003",
            "instructors": [
                "Ward,Paul A S"
            ],
            "weekdays": "F",
            "start_date": "11/27",
            "room": "301",
            "end_time": "16:20",
            "enrollment_total": 155,
            "class_number": 4841,
            "start_time": "15:30",
            "subject": "ECE"
        },
        {
            "building": "RCH",
            "term": 1159,
            "last_updated": "2015-08-19T22:05:22-04:00",
            "catalog_number": "102",
            "end_date": null,
            "title": "Introduction to Environment and Business",
            "section": "LEC 001",
            "instructors": [
                "Lynes,Jennifer Kristin"
            ],
            "weekdays": "MW",
            "start_date": null,
            "room": "301",
            "end_time": "17:20",
            "enrollment_total": 109,
            "class_number": 5704,
            "start_time": "16:30",
            "subject": "ENBUS"
        },
        {
            "building": "RCH",
            "term": 1159,
            "last_updated": "2015-08-19T22:05:50-04:00",
            "catalog_number": "119",
            "end_date": "09/25",
            "title": "Problems Seminar",
            "section": "SEM 005",
            "instructors": [],
            "weekdays": "F",
            "start_date": "09/25",
            "room": "301",
            "end_time": "15:20",
            "enrollment_total": 0,
            "class_number": 5019,
            "start_time": "14:30",
            "subject": "GENE"
        },
        {
            "building": "RCH",
            "term": 1159,
            "last_updated": "2015-08-19T22:05:50-04:00",
            "catalog_number": "119",
            "end_date": "10/09",
            "title": "Problems Seminar",
            "section": "SEM 005",
            "instructors": [],
            "weekdays": "F",
            "start_date": "10/09",
            "room": "301",
            "end_time": "15:20",
            "enrollment_total": 0,
            "class_number": 5019,
            "start_time": "14:30",
            "subject": "GENE"
        },
        {
            "building": "RCH",
            "term": 1159,
            "last_updated": "2015-08-19T22:05:50-04:00",
            "catalog_number": "119",
            "end_date": "11/06",
            "title": "Problems Seminar",
            "section": "SEM 005",
            "instructors": [],
            "weekdays": "F",
            "start_date": "11/06",
            "room": "301",
            "end_time": "15:20",
            "enrollment_total": 0,
            "class_number": 5019,
            "start_time": "14:30",
            "subject": "GENE"
        },
        {
            "building": "RCH",
            "term": 1159,
            "last_updated": "2015-08-19T22:05:50-04:00",
            "catalog_number": "119",
            "end_date": "09/23",
            "title": "Problems Seminar",
            "section": "SEM 006",
            "instructors": [],
            "weekdays": "W",
            "start_date": "09/23",
            "room": "301",
            "end_time": "16:20",
            "enrollment_total": 0,
            "class_number": 5020,
            "start_time": "15:30",
            "subject": "GENE"
        },
        {
            "building": "RCH",
            "term": 1159,
            "last_updated": "2015-08-19T22:05:50-04:00",
            "catalog_number": "119",
            "end_date": "10/07",
            "title": "Problems Seminar",
            "section": "SEM 006",
            "instructors": [],
            "weekdays": "W",
            "start_date": "10/07",
            "room": "301",
            "end_time": "16:20",
            "enrollment_total": 0,
            "class_number": 5020,
            "start_time": "15:30",
            "subject": "GENE"
        },
        {
            "building": "RCH",
            "term": 1159,
            "last_updated": "2015-08-19T22:05:50-04:00",
            "catalog_number": "119",
            "end_date": "11/04",
            "title": "Problems Seminar",
            "section": "SEM 006",
            "instructors": [],
            "weekdays": "W",
            "start_date": "11/04",
            "room": "301",
            "end_time": "16:20",
            "enrollment_total": 0,
            "class_number": 5020,
            "start_time": "15:30",
            "subject": "GENE"
        },
        {
            "building": "RCH",
            "term": 1159,
            "last_updated": "2015-08-19T22:06:41-04:00",
            "catalog_number": "116",
            "end_date": "09/29",
            "title": "Calculus 1 for Engineering",
            "section": "LEC 001",
            "instructors": [
                "Hamilton,Jordan"
            ],
            "weekdays": "T",
            "start_date": "09/29",
            "room": "301",
            "end_time": "13:20",
            "enrollment_total": 143,
            "class_number": 6165,
            "start_time": "12:30",
            "subject": "MATH"
        },
        {
            "building": "RCH",
            "term": 1159,
            "last_updated": "2015-08-19T22:06:41-04:00",
            "catalog_number": "116",
            "end_date": "10/13",
            "title": "Calculus 1 for Engineering",
            "section": "LEC 001",
            "instructors": [
                "Hamilton,Jordan"
            ],
            "weekdays": "T",
            "start_date": "10/13",
            "room": "301",
            "end_time": "13:20",
            "enrollment_total": 143,
            "class_number": 6165,
            "start_time": "12:30",
            "subject": "MATH"
        },
        {
            "building": "RCH",
            "term": 1159,
            "last_updated": "2015-08-19T22:06:41-04:00",
            "catalog_number": "116",
            "end_date": "10/27",
            "title": "Calculus 1 for Engineering",
            "section": "LEC 001",
            "instructors": [
                "Hamilton,Jordan"
            ],
            "weekdays": "T",
            "start_date": "10/27",
            "room": "301",
            "end_time": "13:20",
            "enrollment_total": 143,
            "class_number": 6165,
            "start_time": "12:30",
            "subject": "MATH"
        },
        {
            "building": "RCH",
            "term": 1159,
            "last_updated": "2015-08-19T22:06:41-04:00",
            "catalog_number": "116",
            "end_date": "11/10",
            "title": "Calculus 1 for Engineering",
            "section": "LEC 001",
            "instructors": [
                "Hamilton,Jordan"
            ],
            "weekdays": "T",
            "start_date": "11/10",
            "room": "301",
            "end_time": "13:20",
            "enrollment_total": 143,
            "class_number": 6165,
            "start_time": "12:30",
            "subject": "MATH"
        },
        {
            "building": "RCH",
            "term": 1159,
            "last_updated": "2015-08-19T22:06:41-04:00",
            "catalog_number": "116",
            "end_date": "11/24",
            "title": "Calculus 1 for Engineering",
            "section": "LEC 001",
            "instructors": [
                "Hamilton,Jordan"
            ],
            "weekdays": "T",
            "start_date": "11/24",
            "room": "301",
            "end_time": "13:20",
            "enrollment_total": 143,
            "class_number": 6165,
            "start_time": "12:30",
            "subject": "MATH"
        },
        {
            "building": "RCH",
            "term": 1159,
            "last_updated": "2015-08-19T22:06:41-04:00",
            "catalog_number": "116",
            "end_date": null,
            "title": "Calculus 1 for Engineering",
            "section": "LEC 002",
            "instructors": [
                "Andre,Robert"
            ],
            "weekdays": "M",
            "start_date": null,
            "room": "301",
            "end_time": "10:20",
            "enrollment_total": 124,
            "class_number": 6166,
            "start_time": "09:30",
            "subject": "MATH"
        },
        {
            "building": "RCH",
            "term": 1159,
            "last_updated": "2015-08-19T22:06:41-04:00",
            "catalog_number": "116",
            "end_date": null,
            "title": "Calculus 1 for Engineering",
            "section": "LEC 002",
            "instructors": [
                "Andre,Robert"
            ],
            "weekdays": "W",
            "start_date": null,
            "room": "301",
            "end_time": "11:20",
            "enrollment_total": 124,
            "class_number": 6166,
            "start_time": "10:30",
            "subject": "MATH"
        },
        {
            "building": "RCH",
            "term": 1159,
            "last_updated": "2015-08-19T22:06:41-04:00",
            "catalog_number": "116",
            "end_date": null,
            "title": "Calculus 1 for Engineering",
            "section": "LEC 002",
            "instructors": [
                "Andre,Robert"
            ],
            "weekdays": "F",
            "start_date": null,
            "room": "301",
            "end_time": "10:20",
            "enrollment_total": 124,
            "class_number": 6166,
            "start_time": "09:30",
            "subject": "MATH"
        },
        {
            "building": "RCH",
            "term": 1159,
            "last_updated": "2015-08-19T22:06:41-04:00",
            "catalog_number": "116",
            "end_date": "09/21",
            "title": "Calculus 1 for Engineering",
            "section": "LEC 002",
            "instructors": [
                "Andre,Robert"
            ],
            "weekdays": "M",
            "start_date": "09/21",
            "room": "301",
            "end_time": "11:20",
            "enrollment_total": 124,
            "class_number": 6166,
            "start_time": "10:30",
            "subject": "MATH"
        },
        {
            "building": "RCH",
            "term": 1159,
            "last_updated": "2015-08-19T22:06:41-04:00",
            "catalog_number": "116",
            "end_date": "10/05",
            "title": "Calculus 1 for Engineering",
            "section": "LEC 002",
            "instructors": [
                "Andre,Robert"
            ],
            "weekdays": "M",
            "start_date": "10/05",
            "room": "301",
            "end_time": "11:20",
            "enrollment_total": 124,
            "class_number": 6166,
            "start_time": "10:30",
            "subject": "MATH"
        },
        {
            "building": "RCH",
            "term": 1159,
            "last_updated": "2015-08-19T22:06:41-04:00",
            "catalog_number": "116",
            "end_date": "10/19",
            "title": "Calculus 1 for Engineering",
            "section": "LEC 002",
            "instructors": [
                "Andre,Robert"
            ],
            "weekdays": "M",
            "start_date": "10/19",
            "room": "301",
            "end_time": "11:20",
            "enrollment_total": 124,
            "class_number": 6166,
            "start_time": "10:30",
            "subject": "MATH"
        },
        {
            "building": "RCH",
            "term": 1159,
            "last_updated": "2015-08-19T22:06:41-04:00",
            "catalog_number": "116",
            "end_date": "11/02",
            "title": "Calculus 1 for Engineering",
            "section": "LEC 002",
            "instructors": [
                "Andre,Robert"
            ],
            "weekdays": "M",
            "start_date": "11/02",
            "room": "301",
            "end_time": "11:20",
            "enrollment_total": 124,
            "class_number": 6166,
            "start_time": "10:30",
            "subject": "MATH"
        },
        {
            "building": "RCH",
            "term": 1159,
            "last_updated": "2015-08-19T22:06:41-04:00",
            "catalog_number": "116",
            "end_date": "11/16",
            "title": "Calculus 1 for Engineering",
            "section": "LEC 002",
            "instructors": [
                "Andre,Robert"
            ],
            "weekdays": "M",
            "start_date": "11/16",
            "room": "301",
            "end_time": "11:20",
            "enrollment_total": 124,
            "class_number": 6166,
            "start_time": "10:30",
            "subject": "MATH"
        },
        {
            "building": "RCH",
            "term": 1159,
            "last_updated": "2015-08-19T22:06:41-04:00",
            "catalog_number": "116",
            "end_date": "11/30",
            "title": "Calculus 1 for Engineering",
            "section": "LEC 002",
            "instructors": [
                "Andre,Robert"
            ],
            "weekdays": "M",
            "start_date": "11/30",
            "room": "301",
            "end_time": "11:20",
            "enrollment_total": 124,
            "class_number": 6166,
            "start_time": "10:30",
            "subject": "MATH"
        },
        {
            "building": "RCH",
            "term": 1159,
            "last_updated": "2015-08-19T22:06:41-04:00",
            "catalog_number": "117",
            "end_date": null,
            "title": "Calculus 1 for Engineering",
            "section": "LEC 002",
            "instructors": [
                "Kennedy,Matthew"
            ],
            "weekdays": "MWF",
            "start_date": null,
            "room": "301",
            "end_time": "12:20",
            "enrollment_total": 142,
            "class_number": 6010,
            "start_time": "11:30",
            "subject": "MATH"
        },
        {
            "building": "RCH",
            "term": 1159,
            "last_updated": "2015-08-19T22:06:41-04:00",
            "catalog_number": "117",
            "end_date": "10/02",
            "title": "Calculus 1 for Engineering",
            "section": "LEC 002",
            "instructors": [
                "Kennedy,Matthew"
            ],
            "weekdays": "F",
            "start_date": "10/02",
            "room": "301",
            "end_time": "15:20",
            "enrollment_total": 142,
            "class_number": 6010,
            "start_time": "14:30",
            "subject": "MATH"
        },
        {
            "building": "RCH",
            "term": 1159,
            "last_updated": "2015-08-19T22:06:41-04:00",
            "catalog_number": "117",
            "end_date": "10/16",
            "title": "Calculus 1 for Engineering",
            "section": "LEC 002",
            "instructors": [
                "Kennedy,Matthew"
            ],
            "weekdays": "F",
            "start_date": "10/16",
            "room": "301",
            "end_time": "15:20",
            "enrollment_total": 142,
            "class_number": 6010,
            "start_time": "14:30",
            "subject": "MATH"
        },
        {
            "building": "RCH",
            "term": 1159,
            "last_updated": "2015-08-19T22:06:41-04:00",
            "catalog_number": "117",
            "end_date": "10/30",
            "title": "Calculus 1 for Engineering",
            "section": "LEC 002",
            "instructors": [
                "Kennedy,Matthew"
            ],
            "weekdays": "F",
            "start_date": "10/30",
            "room": "301",
            "end_time": "15:20",
            "enrollment_total": 142,
            "class_number": 6010,
            "start_time": "14:30",
            "subject": "MATH"
        },
        {
            "building": "RCH",
            "term": 1159,
            "last_updated": "2015-08-19T22:06:41-04:00",
            "catalog_number": "117",
            "end_date": "11/13",
            "title": "Calculus 1 for Engineering",
            "section": "LEC 002",
            "instructors": [
                "Kennedy,Matthew"
            ],
            "weekdays": "F",
            "start_date": "11/13",
            "room": "301",
            "end_time": "15:20",
            "enrollment_total": 142,
            "class_number": 6010,
            "start_time": "14:30",
            "subject": "MATH"
        },
        {
            "building": "RCH",
            "term": 1159,
            "last_updated": "2015-08-19T22:06:41-04:00",
            "catalog_number": "117",
            "end_date": "11/27",
            "title": "Calculus 1 for Engineering",
            "section": "LEC 002",
            "instructors": [
                "Kennedy,Matthew"
            ],
            "weekdays": "F",
            "start_date": "11/27",
            "room": "301",
            "end_time": "15:20",
            "enrollment_total": 142,
            "class_number": 6010,
            "start_time": "14:30",
            "subject": "MATH"
        },
        {
            "building": "RCH",
            "term": 1159,
            "last_updated": "2015-08-19T22:06:41-04:00",
            "catalog_number": "117",
            "end_date": null,
            "title": "Calculus 1 for Engineering",
            "section": "LEC 003",
            "instructors": [
                "Harmsworth,David L"
            ],
            "weekdays": "M",
            "start_date": null,
            "room": "301",
            "end_time": "15:20",
            "enrollment_total": 154,
            "class_number": 6011,
            "start_time": "14:30",
            "subject": "MATH"
        },
        {
            "building": "RCH",
            "term": 1159,
            "last_updated": "2015-08-19T22:06:41-04:00",
            "catalog_number": "117",
            "end_date": null,
            "title": "Calculus 1 for Engineering",
            "section": "LEC 003",
            "instructors": [
                "Harmsworth,David L"
            ],
            "weekdays": "T",
            "start_date": null,
            "room": "301",
            "end_time": "12:20",
            "enrollment_total": 154,
            "class_number": 6011,
            "start_time": "11:30",
            "subject": "MATH"
        },
        {
            "building": "RCH",
            "term": 1159,
            "last_updated": "2015-08-19T22:06:41-04:00",
            "catalog_number": "117",
            "end_date": null,
            "title": "Calculus 1 for Engineering",
            "section": "LEC 003",
            "instructors": [
                "Harmsworth,David L"
            ],
            "weekdays": "W",
            "start_date": null,
            "room": "301",
            "end_time": "14:20",
            "enrollment_total": 154,
            "class_number": 6011,
            "start_time": "13:30",
            "subject": "MATH"
        },
        {
            "building": "RCH",
            "term": 1159,
            "last_updated": "2015-08-19T22:06:41-04:00",
            "catalog_number": "117",
            "end_date": "09/30",
            "title": "Calculus 1 for Engineering",
            "section": "LEC 003",
            "instructors": [
                "Harmsworth,David L"
            ],
            "weekdays": "W",
            "start_date": "09/30",
            "room": "301",
            "end_time": "16:20",
            "enrollment_total": 154,
            "class_number": 6011,
            "start_time": "15:30",
            "subject": "MATH"
        },
        {
            "building": "RCH",
            "term": 1159,
            "last_updated": "2015-08-19T22:06:41-04:00",
            "catalog_number": "117",
            "end_date": "10/14",
            "title": "Calculus 1 for Engineering",
            "section": "LEC 003",
            "instructors": [
                "Harmsworth,David L"
            ],
            "weekdays": "W",
            "start_date": "10/14",
            "room": "301",
            "end_time": "16:20",
            "enrollment_total": 154,
            "class_number": 6011,
            "start_time": "15:30",
            "subject": "MATH"
        },
        {
            "building": "RCH",
            "term": 1159,
            "last_updated": "2015-08-19T22:06:41-04:00",
            "catalog_number": "117",
            "end_date": "10/28",
            "title": "Calculus 1 for Engineering",
            "section": "LEC 003",
            "instructors": [
                "Harmsworth,David L"
            ],
            "weekdays": "W",
            "start_date": "10/28",
            "room": "301",
            "end_time": "16:20",
            "enrollment_total": 154,
            "class_number": 6011,
            "start_time": "15:30",
            "subject": "MATH"
        },
        {
            "building": "RCH",
            "term": 1159,
            "last_updated": "2015-08-19T22:06:41-04:00",
            "catalog_number": "117",
            "end_date": "11/11",
            "title": "Calculus 1 for Engineering",
            "section": "LEC 003",
            "instructors": [
                "Harmsworth,David L"
            ],
            "weekdays": "W",
            "start_date": "11/11",
            "room": "301",
            "end_time": "16:20",
            "enrollment_total": 154,
            "class_number": 6011,
            "start_time": "15:30",
            "subject": "MATH"
        },
        {
            "building": "RCH",
            "term": 1159,
            "last_updated": "2015-08-19T22:06:41-04:00",
            "catalog_number": "117",
            "end_date": "11/25",
            "title": "Calculus 1 for Engineering",
            "section": "LEC 003",
            "instructors": [
                "Harmsworth,David L"
            ],
            "weekdays": "W",
            "start_date": "11/25",
            "room": "301",
            "end_time": "16:20",
            "enrollment_total": 154,
            "class_number": 6011,
            "start_time": "15:30",
            "subject": "MATH"
        },
        {
            "building": "RCH",
            "term": 1159,
            "last_updated": "2015-08-19T22:06:43-04:00",
            "catalog_number": "227",
            "end_date": null,
            "title": "Calculus 3 for Honours Physics",
            "section": "TUT 101",
            "instructors": [
                "Marshman,Beverly J"
            ],
            "weekdays": "M",
            "start_date": null,
            "room": "301",
            "end_time": "18:20",
            "enrollment_total": 110,
            "class_number": 5952,
            "start_time": "17:30",
            "subject": "MATH"
        },
        {
            "building": "RCH",
            "term": 1159,
            "last_updated": "2015-08-19T22:08:51-04:00",
            "catalog_number": "380",
            "end_date": null,
            "title": "Introduction to Feedback Control",
            "section": "LEC 001",
            "instructors": [
                "Thistle,John"
            ],
            "weekdays": "MWF",
            "start_date": null,
            "room": "301",
            "end_time": "13:20",
            "enrollment_total": 117,
            "class_number": 8010,
            "start_time": "12:30",
            "subject": "SE"
        },
        {
            "building": "RCH",
            "term": 1159,
            "last_updated": "2015-08-19T22:08:51-04:00",
            "catalog_number": "380",
            "end_date": null,
            "title": "Introduction to Feedback Control",
            "section": "TUT 101",
            "instructors": [
                "Thistle,John"
            ],
            "weekdays": "Th",
            "start_date": null,
            "room": "301",
            "end_time": "12:20",
            "enrollment_total": 117,
            "class_number": 8011,
            "start_time": "11:30",
            "subject": "SE"
        }
    ]
}